Workbook
Name DATA: #REF!
Name z: 'SQURPHARMA Earnings Model T-1'!$AA$85

Sheet SQURPHARMA Earnings Model T-1
B2: SQUARE PHARMACUTICALS PLC.
B3: DSE: SQURPHARMA | BN3: GR
B4: PREPARED BY: GROUP 04
B6: Implied DDM target value | C6: =DDM!C18 -> 204.37351
B7: Implied P/E 12-month target value | C7: =C256 -> 381.43069
B8: Implied DCF 12-month target value | C8: =C285 -> 323.0198
B9: Implied target value | C9: =0.6*C6+0.2*C7+0.2*C8 -> 263.5142
B10: Implied target price band | C10: BDT 248.43 to BDT 279.79
B13: Income Statement | D13: Sept-20 | E13: Dec-20 | F13: Mar-21 | G13: Jun-21 | H13: Jun-21 | I13: Sept-21 | J13: Dec-21 | K13: Mar-22 | L13: Jun-22 | M13: Jun-22 | N13: Sept-22 | O13: Dec-22 | P13: Mar-23 | Q13: Jun-23 | R13: Jun-23 | S13: Sept-23 | T13: Dec-23 | U13: Mar-24 | V13: Jun-24 | W13: Jun-24 | X13: Sept-24 | Y13: Dec-24 | Z13: Mar-25 | AA13: Jun-25 | AB13: Jun-25 | AC13: Sept-25 | AD13: Dec-25 | AE13: Mar-26 | AF13: Jun-26 | AG13: Jun-26 | AH13: Sept-26 | AI13: Dec-26 | AJ13: Mar-27 | AK13: Jun-27 | AL13: Jun-27 | AM13: Sept-27 | AN13: Dec-27 | AO13: Mar-28 | AP13: Jun-28 | AQ13: Jun-28
B14: (Taka in millions, except per share data) | D14: 1Q21 | E14: 2Q21 | F14: 3Q21 | G14: 4Q21 | H14: 2021 | I14: 1Q22 | J14: 2Q22 | K14: 3Q22 | L14: 4Q22 | M14: 2022 | N14: 1Q23 | O14: 2Q23 | P14: 3Q23 | Q14: 4Q23 | R14: 2023 | S14: 1Q24 | T14: 2Q24 | U14: 3Q24 | V14: 4Q24 | W14: 2024 | X14: 1Q25 | Y14: 2Q25 | Z14: 3Q25 | AA14: 4Q25 E | AB14: 2025E | AC14: 1Q26E | AD14: 2Q26E | AE14: 3Q26E | AF14: 4Q26E | AG14: 2026E | AH14: 1Q27E | AI14: 2Q27E | AJ14: 3Q27E | AK14: 4Q27E | AL14: 2027E | AM14: 1Q28E | AN14: 2Q28E | AO14: 3Q28E | AP14: 4Q28E | AQ14: 2028E
B15: Gross Revenue | D15: 14724.617 | E15: 14354.709 | F15: =(14792615438/1000000) -> 14792.615 | G15: =(58346258281-43871940669)/1000000 -> 14474.318 | H15: =SUM(D15:G15) -> 58346.258 | I15: =(17417537149/1000000) -> 17417.537 | J15: 16432.305 | K15: 16881.356 | L15: 15675.762 | M15: =SUM(I15:L15) -> 66406.96 | N15: =18813280078/1000000 -> 18813.28 | O15: =18715142842/1000000 -> 18715.143 | P15: =18329969468/1000000 -> 18329.969 | Q15: 16476.981 | R15: =SUM(N15:Q15) -> 72335.373 | S15: =21613450761/1000000 -> 21613.451 | T15: =21440318106/1000000 -> 21440.318 | U15: 19809.914 | V15: =W15-SUM(S15:U15) -> 7237.3485 | W15: 70101.031 | X15: 17746.888 | Y15: 19970.891 | Z15: =20128714463/1000000 -> 20128.714 | AA15: =AA17 -> 18711.959 | AB15: =AB17 -> 76558.452 | AC15: =AC17 -> 21962.942 | AD15: =AD17 -> 22162.304 | AE15: =AE17 -> 22070.874 | AF15: =AF17 -> 20811.477 | AG15: =AG17 -> 87023.45 | AH15: =AH17 -> 24965.121 | ... AQ15: =AQ17 -> 112440.46
B16: Less: Value Added Tax | D16: 2149.0359 | E16: 1988.649 | F16: =(2022482749/1000000) -> 2022.4827 | G16: 1483.0617 | H16: =SUM(D16:G16) -> 7643.2294 | I16: =(2540676024/1000000) -> 2540.676 | J16: 2236.9283 | K16: 2231.3547 | L16: 1800.0596 | M16: =SUM(I16:L16) -> 8809.0186 | N16: =2743651781/1000000 -> 2743.6518 | O16: =2528063937/1000000 -> 2528.0639 | P16: =2442606903/1000000 -> 2442.6069 | Q16: 1873.368 | R16: =SUM(N16:Q16) -> 9587.6906 | S16: =3154251600/1000000 -> 3154.2516 | T16: =2921367435/1000000 -> 2921.3674 | U16: 2580.8647 | V16: =W16-SUM(S16:U16) -> -8656.4837 | X16: 0 | Y16: - | Z16: 0 | AA16: 0 | AB16: 0 | AC16: 0 | AD16: 0 | AE16: 0 | AF16: 0 | AG16: 0 | AH16: 0 | AI16: 0 | AJ16: 0 | AK16: 0 | AL16: 0 | AM16: 0 | AN16: 0 | AO16: 0 | AP16: 0 | AQ16: 0
B17: Net Revenue | D17: =D15-D16 -> 12575.581 | E17: =E15-E16 -> 12366.059 | F17: =F15-F16 -> 12770.133 | G17: =G15-G16 -> 12991.256 | H17: =SUM(D17:G17) -> 50703.029 | I17: =I15-I16 -> 14876.861 | J17: =J15-J16 -> 14195.377 | K17: =K15-K16 -> 14650.002 | L17: =L15-L16 -> 13875.702 | M17: =SUM(I17:L17) -> 57597.941 | N17: =N15-N16 -> 16069.628 | O17: =O15-O16 -> 16187.079 | P17: =P15-P16 -> 15887.363 | Q17: 14603.613 | R17: =SUM(N17:Q17) -> 62747.683 | S17: =S15-S16 -> 18459.199 | T17: =T15-T16 -> 18518.951 | U17: =U15-U16 -> 17229.049 | V17: =W17-SUM(S17:U17) -> 15893.832 | W17: 70101.031 | X17: =X15-X16 -> 17746.888 | Y17: 19970.891 | Z17: =Z15-Z16 -> 20128.714 | AA17: =Z17*(1+Workings!F10) -> 18711.959 | AB17: =SUM(X17:AA17) -> 76558.452 | AC17: =$AG$17*Workings!C19 -> 21962.942 | AD17: =$AG$17*Workings!D19 -> 22162.304 | AE17: =$AG$17*Workings!E19 -> 22070.874 | AF17: =$AG$17*Workings!F19 -> 20811.477 | AG17: =AB17*(1+Workings!Y6) -> 87023.45 | AH17: =Workings!C19*$AL$17 -> 24965.121 | AI17: =Workings!D19*$AL$17 -> 25191.734 | AJ17: =Workings!E19*$AL$17 -> 25087.806 | AK17: =Workings!F19*$AL$17 -> 23656.259 | AL17: =AG17*(1+Workings!Y6) -> 98918.938 | AM17: =Workings!C19*$AQ$17 -> 28377.676 | AN17: =Workings!D19*$AQ$17 -> 28635.265 | AO17: =Workings!E19*$AQ$17 -> 28517.131 | AP17: =Workings!F19*$AQ$17 -> 26889.902 | AQ17: =AL17*(1+Workings!Y6) -> 112440.46
B18: Cost of sales | D18: 6154.0513 | E18: 5757.9131 | F18: =(6230986835/1000000) -> 6230.9868 | G18: 6657.0844 | H18: =SUM(D18:G18) -> 24800.036 | I18: =(7263066871/1000000) -> 7263.0669 | J18: 6609.6795 | K18: 7125.5805 | L18: 6959.7001 | M18: =SUM(I18:L18) -> 27958.027 | N18: =7782604676/1000000 -> 7782.6047 | O18: =7607825295/1000000 -> 7607.8253 | P18: =8214266551/1000000 -> 8214.2666 | Q18: 8167.3968 | R18: =SUM(N18:Q18) -> 31772.093 | S18: =8689972839/1000000 -> 8689.9728 | T18: =9463751431/1000000 -> 9463.7514 | U18: 8401.0036 | V18: =W18-SUM(S18:U18) -> 10473.874 | W18: 37028.602 | X18: 8828.4597 | Y18: 11064.972 | Z18: =10451313698/1000000 -> 10451.314 | AA18: =AA17-AA19 -> 10431.917 | AB18: =AB17-AB19 -> 40776.662 | AC18: =AC17-AC19 -> 10673.99 | AD18: =AD17-AD19 -> 10948.178 | AE18: =AE17-AE19 -> 11079.579 | AF18: =AF17-AF19 -> 11602.399 | AG18: =AG17-AG19 -> 44319.997 | AH18: =AH17-AH19 -> 12133.049 | ... AQ18: =AQ17-AQ19 -> 57264.573
B19: Gross Profit | D19: =D17-D18 -> 6421.5295 | E19: =E17-E18 -> 6608.1464 | F19: =F17-F18 -> 6539.1459 | G19: =G17-G18 -> 6334.1716 | H19: =H17-H18 -> 25902.993 | I19: =I17-I18 -> 7613.7943 | J19: =J17-J18 -> 7585.6972 | K19: =K17-K18 -> 7524.421 | ... U19: =U17-U18 -> 8828.0456 | V19: =W19-SUM(S19:U19) -> 5419.9585 | W19: 33072.43 | X19: =X17-X18 -> 8918.4278 | Y19: =Y17-Y18 -> 8905.9195 | Z19: =Z17-Z18 -> 9677.4008 | AA19: =AA17*Workings!F28 -> 8280.0419 | AB19: =SUM(X19:AA19) -> 35781.79 | AC19: =AC17*Workings!C28 -> 11288.952 | AD19: =AD17*Workings!D28 -> 11214.126 | AE19: =AE17*Workings!E28 -> 10991.295 | AF19: =AF17*Workings!F28 -> 9209.0788 | AG19: =SUM(AC19:AF19) -> 42703.452 | AH19: =AH17*Workings!C28 -> 12832.072 | AI19: =AI17*Workings!D28 -> 12747.017 | AJ19: =AJ17*Workings!E28 -> 12493.727 | AK19: =AK17*Workings!F28 -> 10467.895 | AL19: =SUM(AH19:AK19) -> 48540.711 | AM19: =AM17*Workings!C28 -> 14586.125 | AN19: =AN17*Workings!D28 -> 14489.444 | AO19: =AO17*Workings!E28 -> 14201.531 | AP19: =AP17*Workings!F28 -> 11898.781 | AQ19: =SUM(AM19:AP19) -> 55175.882
B20: Selling and Distribution Expenses | D20: 1915.6002 | E20: 2111.4744 | F20: =(2145689022/1000000) -> 2145.689 | G20: 2391.7088 | H20: =SUM(D20:G20) -> 8564.4725 | I20: =(2227930097/1000000) -> 2227.9301 | J20: 2492.5 | K20: 2443.422 | L20: 3275.4184 | M20: =SUM(I20:L20) -> 10439.27 | N20: =2609458904/1000000 -> 2609.4589 | O20: =2952183775/1000000 -> 2952.1838 | P20: =3046114879/1000000 -> 3046.1149 | Q20: 3206.5306 | R20: =SUM(N20:Q20) -> 11814.288 | S20: =3130077739/1000000 -> 3130.0777 | T20: =3566401521/1000000 -> 3566.4015 | U20: 3945.507 | V20: =W20-SUM(S20:U20) -> 1423.9171 | W20: 12065.903 | X20: 3057.5385 | Y20: 2987.8914 | Z20: =3919806144/1000000 -> 3919.8061 | AA20: =AA17*AA56 -> 3309.0792 | AB20: =SUM(X20:AA20) -> 13274.315 | AC20: =AC17*AC56 -> 3883.9928 | AD20: =AD17*AD56 -> 3919.2486 | AE20: =AE17*AE56 -> 3903.0798 | AF20: =AF17*AF56 -> 3680.3643 | AG20: =SUM(AC20:AF20) -> 15386.686 | AH20: =AH17*AH56 -> 4414.9071 | AI20: =AI17*AI56 -> 4454.9821 | AJ20: =AJ17*AJ56 -> 4436.6032 | AK20: =AK17*AK56 -> 4183.444 | AL20: =SUM(AH20:AK20) -> 17489.936 | AM20: =AM17*AM56 -> 5018.3936 | AN20: =AN17*AN56 -> 5063.9465 | AO20: =AO17*AO56 -> 5043.0553 | AP20: =AP17*AP56 -> 4755.2912 | AQ20: =SUM(AM20:AP20) -> 19880.687
B21: Administrative Expenses | D21: 250.24563 | E21: 302.39043 | F21: =(316712596/1000000) -> 316.7126 | G21: 347.58293 | H21: =SUM(D21:G21) -> 1216.9316 | I21: =(264530012/1000000) -> 264.53001 | J21: 338.37101 | K21: 350.04053 | L21: 449.31262 | M21: =SUM(I21:L21) -> 1402.2542 | N21: =344539083/1000000 -> 344.53908 | O21: =381461263/1000000 -> 381.46126 | P21: =354002820/1000000 -> 354.00282 | Q21: 455.98795 | R21: =SUM(N21:Q21) -> 1535.9911 | S21: =339315089/1000000 -> 339.31509 | T21: =421752028/1000000 -> 421.75203 | U21: 407.38711 | V21: =W21-SUM(S21:U21) -> 701.47735 | W21: 1869.9316 | X21: 439.34631 | Y21: 444.96885 | Z21: =541475787/1000000 -> 541.47579 | AA21: =AA19*AA57 -> 206.88902 | AB21: =SUM(X21:AA21) -> 1632.68 | AC21: =AC17*AC57 -> 548.77641 | AD21: =AD17*AD57 -> 553.75775 | AE21: =AE17*AE57 -> 551.47324 | AF21: =AF17*AF57 -> 520.00536 | AG21: =SUM(AC21:AF21) -> 2174.0128 | AH21: =AH17*AH57 -> 623.79025 | AI21: =AI17*AI57 -> 629.45251 | AJ21: =AJ17*AJ57 -> 626.85572 | AK21: =AK17*AK57 -> 591.08641 | AL21: =SUM(AH21:AK21) -> 2471.1849 | AM21: =AM17*AM57 -> 709.05795 | AN21: =AN17*AN57 -> 715.49421 | AO21: =AO17*AO57 -> 712.54245 | AP21: =AP17*AP57 -> 671.88373 | AQ21: =SUM(AM21:AP21) -> 2808.9783
B22: Finance Cost | D22: 0.005285 | E22: 0 | F22: =(3887/1000000) -> 0.003887 | G22: 0.004271 | H22: =SUM(D22:G22) -> 0.013443 | I22: =(22214/1000000) -> 0.022214 | J22: 0.000695 | K22: 0.002491 | L22: 0.004357 | M22: =SUM(I22:L22) -> 0.029757 | N22: 0 | O22: =33758257/1000000 -> 33.758257 | P22: =42164730/1000000 -> 42.16473 | Q22: 43.043792 | R22: =SUM(N22:Q22) -> 118.96678 | S22: =41401812/1000000 -> 41.401812 | T22: =58267267/1000000 -> 58.267267 | U22: 71.943996 | V22: =W22-SUM(S22:U22) -> 72.385355 | W22: 243.99843 | X22: 68.795526 | Y22: 58.405306 | Z22: =49502042/1000000 -> 49.502042 | AA22: =AA19*AA55 -> 25.1459 | AB22: =SUM(X22:AA22) -> 201.84877 | AC22: =AC19*AC55 -> 34.283748 | AD22: =AD19*AD55 -> 34.056505 | AE22: =AE19*AE55 -> 33.379785 | AF22: =AF19*AF55 -> 27.967319 | AG22: =SUM(AC22:AF22) -> 129.68736 | AH22: =AH19*AH55 -> 38.970093 | AI22: =AI19*AI55 -> 38.711788 | AJ22: =AJ19*AJ55 -> 37.942564 | AK22: =AK19*AK55 -> 31.790253 | AL22: =SUM(AH22:AK22) -> 147.4147 | AM22: =AM19*AM55 -> 44.297028 | AN22: =AN19*AN55 -> 44.003415 | AO22: =AO19*AO55 -> 43.129044 | AP22: =AP19*AP55 -> 36.135756 | AQ22: =SUM(AM22:AP22) -> 167.56524
B23: Total operating expenses | D23: =SUM(D20:D22) -> 2165.8512 | E23: =SUM(E20:E22) -> 2413.8648 | F23: =SUM(F20:F22) -> 2462.4055 | G23: =SUM(G20:G22) -> 2739.296 | H23: =SUM(H20:H22) -> 9781.4175 | I23: =SUM(I20:I22) -> 2492.4823 | J23: =SUM(J20:J22) -> 2830.8717 | K23: =SUM(K20:K22) -> 2793.465 | ... U23: =SUM(U20:U22) -> 4424.8381 | V23: =W23-SUM(S23:U23) -> 2197.7798 | W23: 14179.833 | X23: =SUM(X20:X22) -> 3565.6803 | Y23: =SUM(Y20:Y22) -> 3491.2656 | Z23: =SUM(Z20:Z22) -> 4510.784 | AA23: =SUM(AA20:AA22) -> 3541.1141 | AB23: =SUM(AB20:AB22) -> 15108.844 | AC23: =SUM(AC20:AC22) -> 4467.053 | AD23: =SUM(AD20:AD22) -> 4507.0628 | AE23: =SUM(AE20:AE22) -> 4487.9329 | ... AQ23: =SUM(AQ20:AQ22) -> 22857.23
B24: Other Operating Income | D24: 0 | E24: 11.116534 | F24: =(47254323/1000000) -> 47.254323 | G24: 49.295353 | H24: =SUM(D24:G24) -> 107.66621 | I24: =(50626126/1000000) -> 50.626126 | J24: 38.721032 | K24: 45.548721 | L24: 483.22127 | M24: =SUM(I24:L24) -> 618.11715 | N24: =455401465/1000000 -> 455.40146 | O24: =91502667/1000000 -> 91.502667 | P24: =193771112/1000000 -> 193.77111 | Q24: -25.350493 | R24: =SUM(N24:Q24) -> 715.32475 | S24: =115547205/1000000 -> 115.54721 | T24: =12880354/1000000 -> 12.880354 | U24: 31.250174 | V24: =W24-SUM(S24:U24) -> 179.00826 | W24: 338.68599 | X24: 211.25538 | Y24: 16.521154 | Z24: =149643186/1000000 -> 149.64319 | AA24: =AVERAGE(V24,X24:Z24) -> 139.107 | AB24: =SUM(X24:AA24) -> 516.52671 | AC24: =AVERAGE(X24:AA24) -> 129.13168 | AD24: =AVERAGE(Y24:AA24,AC24) -> 108.60075 | AE24: =AVERAGE(Z24:AA24,AC24:AD24) -> 131.62065 | AF24: =AVERAGE(AA24,AC24:AE24) -> 127.11502 | AG24: =SUM(AC24:AF24) -> 496.46811 | AH24: =AVERAGE(AC24:AF24) -> 124.11703 | AI24: =AVERAGE(AH24,AD24:AF24) -> 122.86336 | AJ24: =AVERAGE(AH24:AI24,AE24:AF24) -> 126.42902 | AK24: =AVERAGE(AH24:AJ24,AF24) -> 125.13111 | AL24: =SUM(AH24:AK24) -> 498.54051 | AM24: =AVERAGE(AH24:AK24) -> 124.63513 | AN24: =AVERAGE(AM24,AI24:AK24) -> 124.76465 | AO24: =AVERAGE(AM24:AN24,AJ24:AK24) -> 125.23998 | AP24: =AVERAGE(AM24:AO24,AK24) -> 124.94272 | AQ24: =SUM(AM24,AN24,AO24,AP24) -> 499.58247
B25: Profit from Operations | D25: =D19-D23+D24 -> 4255.6784 | E25: =E19-E23+E24 -> 4205.3981 | F25: =F19-F23+F24 -> 4123.9947 | G25: =G19-G23+G24 -> 3644.1709 | H25: =H19-H23+H24 -> 16229.242 | I25: =I19-I23+I24 -> 5171.9381 | J25: =J19-J23+J24 -> 4793.5465 | K25: =K19-K23+K24 -> 4776.5048 | ... U25: =U19-U23+U24 -> 4434.4576 | V25: =W25-SUM(S25:U25) -> 3401.187 | W25: 19231.282 | X25: =X19-X23+X24 -> 5564.0029 | Y25: =Y19-Y23+Y24 -> 5431.1751 | Z25: =Z19-Z23+Z24 -> 5316.26 | AA25: =AA19-AA23+AA24 -> 4878.0348 | AB25: =SUM(X25:AA25) -> 21189.473 | AC25: =AC19-AC23+AC24 -> 6951.031 | AD25: =AD19-AD23+AD24 -> 6815.6638 | AE25: =AE19-AE23+AE24 -> 6634.9831 | AF25: =AF19-AF23+AF24 -> 5107.8568 | AG25: =AG19-AG23+AG24 -> 25509.535 | AH25: =AH19-AH23+AH24 -> 7878.5216 | AI25: =AI19-AI23+AI24 -> 7746.7344 | AJ25: =AJ19-AJ23+AJ24 -> 7518.755 | ... AQ25: =AQ19-AQ23+AQ24 -> 32818.235
B26: Interest income | AA26: =(AA82+AA90)*AA61 -> 1127.7505 | AB26: =AA26 -> 1127.7505 | AC26: =(AC82+AC90)*AC61 -> 1022.8181 | AD26: =(AD82+AD90)*AD61 -> 856.42267 | AE26: =(AE82+AE90)*AE61 -> 596.30121 | AF26: =(AF82+AF90)*AF61 -> 737.6353 | AG26: =SUM(AC26:AF26) -> 3213.1773 | AH26: =(AH82+AH90)*AH61 -> 733.5222 | AI26: =(AI82+AI90)*AI61 -> 749.57325 | AJ26: =(AJ82+AJ90)*AJ61 -> 707.23363 | AK26: =(AK82+AK90)*AK61 -> 755.96217 | AL26: =SUM(AH26:AK26) -> 2946.2913 | AM26: =(AM82+AM90)*AM61 -> 770.26331 | AN26: =(AN82+AN90)*AN61 -> 722.11836 | AO26: =(AO82+AO90)*AO61 -> 752.16644 | AP26: =(AP82+AP90)*AP61 -> 792.23797 | AQ26: =SUM(AM26:AP26) -> 3036.7861
B27: Dividend income | D27: 114.14133 | E27: 50.363595 | F27: 28.495071 | G27: 227 | H27: 420 | I27: 26 | J27: 9.835709 | K27: 205.92337 | L27: 153.25271 | M27: 395.01179 | N27: 24.236982 | O27: 23.92075 | P27: 428.84227 | Q27: 75.966126 | R27: 552.96613 | S27: 15 | T27: -0.183705 | AA27: =AA62*(AA82+AA90) -> 0 | AB27: =AB62*(AB82+AB90) -> 0 | AC27: =AC62*(AC82+AC90) -> 0 | AD27: =AD62*(AD82+AD90) -> 0 | AE27: =AE62*(AE82+AE90) -> 0 | AF27: =AF62*(AF82+AF90) -> 0 | AG27: =AG62*(AG82+AG90) -> 0 | AH27: =AH62*(AH82+AH90) -> 0 | ... AQ27: =AQ62*(AQ82+AQ90) -> 0
B28: Interest expense
B29: Income from investment | U29: 1155.0906 | W29: 4650.6194 | X29: 1464.2206 | Y29: 1591.8902 | Z29: 1507.8212 | AA29: =AVERAGE(V29,X29:Z29) -> 1521.3107 | AB29: =SUM(X29:AA29) -> 6085.2427 | AC29: =AVERAGE(X29:AA29) -> 1521.3107 | AD29: =AVERAGE(Y29:AA29,AC29) -> 1535.5832 | AE29: =AVERAGE(Z29:AA29,AC29:AD29) -> 1521.5064 | AF29: =AVERAGE(AA29,AC29:AE29) -> 1524.9277 | AG29: =SUM(AC29:AF29) -> 6103.328 | AH29: =AVERAGE(AC29:AF29) -> 1525.832 | AI29: =AVERAGE(AD29:AF29,AH29) -> 1526.9623 | AJ29: =AVERAGE(AE29:AF29,AH29:AI29) -> 1524.8071 | AK29: =AVERAGE(AF29,AH29:AJ29) -> 1525.6323 | AL29: =SUM(AH29:AK29) -> 6103.2338 | AM29: =AVERAGE(AH29:AK29) -> 1525.8084 | AN29: =AVERAGE(AI29:AK29,AM29) -> 1525.8026 | AO29: =AVERAGE(AJ29:AK29,AM29:AN29) -> 1525.5126 | AP29: =AVERAGE(AK29,AM29:AO29) -> 1525.689 | AQ29: =SUM(AM29:AP29) -> 6102.8126
B30: Other income/(expense) | D30: 799.73438 | E30: 708.70572 | F30: 727.26467 | G30: 721.75677 | H30: 2957.4615 | I30: 925.53435 | J30: 722.6965 | K30: 557.99992 | L30: 786.94363 | M30: 2993.1744 | N30: 940.83065 | O30: 902.64293 | P30: 546.63476 | Q30: 1014.1805 | R30: 3404.2888 | S30: 1072.4067 | T30: 1050.4658
B31: Total other income/(expense) | D31: =SUM(D26:D30) -> 913.87572 | E31: =SUM(E26:E30) -> 759.06931 | F31: =SUM(F26:F30) -> 755.75974 | G31: =SUM(G26:G30) -> 948.75677 | H31: =SUM(D31:G31) -> 3377.4615 | I31: =SUM(I26:I30) -> 951.53435 | J31: =SUM(J26:J30) -> 732.53221 | K31: =SUM(K26:K30) -> 763.92329 | L31: =SUM(L26:L30) -> 940.19633 | M31: =SUM(I31:L31) -> 3388.1862 | N31: =SUM(N26:N30) -> 965.06763 | O31: =SUM(O26:O30) -> 926.56368 | P31: =SUM(P26:P30) -> 975.47703 | Q31: =SUM(Q26:Q30) -> 1090.1466 | R31: =SUM(N31:Q31) -> 3957.2549 | S31: =SUM(S26:S30) -> 1087.4067 | T31: =SUM(T26:T30) -> 1050.2821 | U31: =SUM(U26:U30) -> 1155.0906 | V31: =W31-SUM(S31:U31) -> 1357.84 | W31: 4650.6194 | X31: =X29 -> 1464.2206 | Y31: =Y29 -> 1591.8902 | Z31: =SUM(Z26:Z30) -> 1507.8212 | AA31: =SUM(AA26:AA30) -> 2649.0611 | AB31: =SUM(AB26:AB30) -> 7212.9932 | AC31: =SUM(AC26:AC30) -> 2544.1288 | AD31: =SUM(AD26:AD30) -> 2392.0058 | AE31: =SUM(AE26:AE30) -> 2117.8076 | AF31: =SUM(AF26:AF30) -> 2262.563 | AG31: =SUM(AG26:AG30) -> 9316.5053 | ... AQ31: =SUM(AQ26:AQ30) -> 9139.5987
B32: Profit before WPPF & WF | D32: =D25+D31 -> 5169.5541 | E32: =E25+E31 -> 4964.4675 | F32: =F25+F31 -> 4879.7544 | G32: =G25+G31 -> 4592.9276 | H32: =H25+H31 -> 19606.704 | I32: =I25+I31 -> 6123.4724 | J32: =J25+J31 -> 5526.0787 | K32: =K25+K31 -> 5540.4281 | ... U32: =U25+U31 -> 5589.5482 | V32: =W32-SUM(S32:U32) -> 4759.027 | W32: 23881.902 | X32: =X25+X29 -> 7028.2236 | Y32: 7023.0653 | Z32: =Z25+Z31 -> 6824.0811 | AA32: =AA25+AA31 -> 7527.0959 | AB32: =AB25+AB31 -> 28402.466 | AC32: =AC25+AC31 -> 9495.1598 | AD32: =AD25+AD31 -> 9207.6697 | AE32: =AE25+AE31 -> 8752.7908 | AF32: =AF25+AF31 -> 7370.4198 | AG32: =AG25+AG31 -> 34826.04 | ... AQ32: =AQ25+AQ31 -> 41957.833
B33: Allocation for WPPF & WF | D33: 246.015 | E33: 236.34362 | F33: =(236684022/1000000) -> 236.68402 | G33: 218.75398 | H33: =SUM(D33:G33) -> 937.79663 | I33: =(291962599/1000000) -> 291.9626 | J33: 263.31557 | K33: 273.29174 | L33: 222.65808 | M33: =SUM(I33:L33) -> 1051.228 | N33: =324256049/1000000 -> 324.25605 | O33: =299370246/1000000 -> 299.37025 | P33: =290584973/1000000 -> 290.58497 | Q33: 165.36071 | R33: =SUM(N33:Q33) -> 1079.572 | S33: =360070723/1000000 -> 360.07072 | T33: =292113630/1000000 -> 292.11363 | U33: 281.51513 | V33: =W33-SUM(S33:U33) -> 226.42739 | W33: 1160.1269 | X33: 332.81084 | Y33: 332.99425 | Z33: 337.44474 | AA33: =(AA32*5%)*90% -> 338.71932 | AB33: =SUM(X33:AA33) -> 1341.9692 | AC33: =(AC32*5%)*90% -> 427.28219 | AD33: =(AD32*5%)*90% -> 414.34514 | AE33: =(AE32*5%)*90% -> 393.87558 | AF33: =(AF32*5%)*90% -> 331.66889 | AG33: =SUM(AC33:AF33) -> 1567.1718 | AH33: =(AH32*5%)*90% -> 456.20441 | AI33: =(AI32*5%)*90% -> 451.04715 | AJ33: =(AJ32*5%)*90% -> 438.78581 | AK33: =(AK32*5%)*90% -> 363.07347 | AL33: =SUM(AH33:AK33) -> 1709.1108 | AM33: =(AM32*5%)*90% -> 505.57876 | AN33: =(AN32*5%)*90% -> 496.74086 | AO33: =(AO32*5%)*90% -> 486.25756 | AP33: =(AP32*5%)*90% -> 399.52532 | AQ33: =SUM(AM33:AP33) -> 1888.1025
B34: Profit before Tax | D34: =D32-D33 -> 4923.5391 | E34: =E32-E33 -> 4728.1238 | F34: =F32-F33 -> 4643.0704 | G34: =G32-G33 -> 4374.1737 | H34: =H32-H33 -> 18668.907 | I34: =I32-I33 -> 5831.5098 | J34: =J32-J33 -> 5262.7632 | K34: =K32-K33 -> 5267.1363 | ... U34: =U32-U33 -> 5308.0331 | V34: =W34-SUM(S34:U34) -> 4532.5996 | W34: 22721.775 | X34: =X32-X33 -> 6695.4127 | Y34: =Y32-Y33 -> 6690.0711 | Z34: =Z32-Z33 -> 6486.6364 | AA34: =AA32-AA33 -> 7188.3766 | AB34: =AB32-AB33 -> 27060.497 | AC34: =AC32-AC33 -> 9067.8776 | AD34: =AD32-AD33 -> 8793.3245 | AE34: =AE32-AE33 -> 8358.9152 | ... AQ34: =AQ32-AQ33 -> 40069.731
B35: Provisions for income tax | D35: 1210.658 | E35: 1167.5459 | F35: =(1064321113/1000000) -> 1064.3211 | G35: 744.95693 | H35: =SUM(D35:G35) -> 4187.4819 | I35: =(1264897161/1000000) -> 1264.8972 | J35: 1170.8406 | K35: 1202.3912 | L35: 980.42069 | M35: =SUM(I35:L35) -> 4618.5496 | N35: =1444802572/1000000 -> 1444.8026 | O35: =1312145648/1000000 -> 1312.1456 | P35: =1272406925/1000000 -> 1272.4069 | Q35: 758.27707 | R35: =SUM(N35:Q35) -> 4787.6322 | S35: =1505534771/1000000 -> 1505.5348 | T35: =1060140659/1000000 -> 1060.1407 | U35: 1239.9162 | V35: =W35-SUM(S35:U35) -> -8467.4068 | W35: -4661.8152 | X35: 1211.1837 | Y35: 1213.619 | Z35: 1168.0119 | AA35: =AA34*AA54 -> 1617.3847 | AB35: =SUM(X35:AA35) -> 5210.1994 | AC35: =AC34*AC54 -> 2040.2725 | AD35: =AD34*AD54 -> 1978.498 | AE35: =AE34*AE54 -> 1880.7559 | AF35: =AF34*AF54 -> 1583.719 | AG35: =AG34*AG54 -> 7483.2454 | AH35: =AH34*AH54 -> 2178.3761 | AI35: =AI34*AI54 -> 2153.7501 | AJ35: =AJ34*AJ54 -> 2095.2022 | AK35: =AK34*AK54 -> 1733.6758 | AL35: =SUM(AH35:AK35) -> 8161.0043 | AM35: =AM34*AM54 -> 2414.1386 | AN35: =AN34*AN54 -> 2371.9376 | AO35: =AO34*AO54 -> 2321.8799 | AP35: =AP34*AP54 -> 1907.7334 | AQ35: =AQ34*AQ54 -> 9015.6895
B36: Deferred Tax (Expense) / Income | D36: 15.417306 | E36: 0.250678 | F36: =-(66788674/1000000) -> -66.788674 | G36: 226.43606 | H36: =SUM(D36:G36) -> 175.31537 | I36: =(9275982/1000000) -> 9.275982 | J36: 18.4142 | K36: 3.411963 | L36: -19.615791 | M36: =SUM(I36:L36) -> 11.486354 | N36: =21152969/1000000 -> 21.152969 | O36: =-8366505/1000000 -> -8.366505 | P36: =(-3854243)/1000000 -> -3.854243 | Q36: 136.97557 | R36: =SUM(N36:Q36) -> 145.90779 | S36: =44874357/1000000 -> 44.874357 | T36: =-126999229/1000000 -> -126.99923 | U36: 346.49914 | V36: =W36-SUM(S36:U36) -> 8.549153 | W36: 272.92342 | X36: 39.459092 | Y36: 29.440774 | Z36: 22.260111 | AA36: =AA34*AA59 -> 156.20324 | AB36: =SUM(X36:AA36) -> 247.36322 | AC36: =AC34*AC59 -> 36.679104 | AD36: =AD34*AD59 -> -27.137859 | AE36: =AE34*AE59 -> 90.642073 | AF36: =AF34*AF59 -> 152.95188 | AG36: =SUM(AC36:AF36) -> 253.1352 | AH36: =AH34*AH59 -> 39.161869 | AI36: =AI34*AI59 -> -29.541686 | AJ36: =AJ34*AJ59 -> 119.96621 | AK36: =AK34*AK59 -> 167.43437 | AL36: =SUM(AH36:AK36) -> 297.02076 | AM36: =AM34*AM59 -> 50.286739 | AN36: =AN34*AN59 -> -32.534431 | AO36: =AO34*AO59 -> 246.71937 | AP36: =AP34*AP59 -> 184.24444 | AQ36: =SUM(AM36:AP36) -> 448.71612
B37: Profit after Tax | D37: =D34-D35+D36 -> 3728.2983 | E37: =E34-E35+E36 -> 3560.8286 | F37: =F34-F35+F36 -> 3511.9606 | G37: =G34-G35+G36 -> 3855.6528 | H37: =H34-H35+H36 -> 14656.74 | I37: =I34-I35+I36 -> 4575.8886 | J37: =J34-J35+J36 -> 4110.3367 | K37: =K34-K35+K36 -> 4068.1571 | ... U37: =U34-U35+U36 -> 4414.6161 | V37: =W37-SUM(S37:U37) -> 3684.9252 | W37: 18332.883 | X37: =X34-X35+X36 -> 5523.6881 | Y37: =Y34-Y35+Y36 -> 5505.8929 | Z37: =Z34-Z35+Z36 -> 5340.8846 | AA37: =AA34-AA35+AA36 -> 5727.1951 | AB37: =AB34-AB35+AB36 -> 22097.661 | AC37: =AC34-AC35+AC36 -> 7064.2843 | AD37: =AD34-AD35+AD36 -> 6787.6887 | AE37: =AE34-AE35+AE36 -> 6568.8013 | ... AQ37: =AQ34-AQ35+AQ36 -> 31502.758
B38: Profit from Associate Undertakings | D38: 203.66715 | E38: 277.30223 | F38: =(350102323/1000000) -> 350.10232 | G38: 460.14 | H38: =SUM(D38:G38) -> 1291.2117 | I38: =(420757631/1000000) -> 420.75763 | J38: 534.01687 | K38: 501.37679 | L38: 554.6563 | M38: =SUM(I38:L38) -> 2010.8076 | N38: 494.7041 | O38: 516 | P38: =449656818/1000000 -> 449.65682 | Q38: 1062.0366 | R38: =SUM(N38:Q38) -> 2522.3975 | S38: 360 | T38: =652559010/1000000 -> 652.55901 | U38: 508.98032 | V38: =W38-SUM(S38:U38) -> 1073.0235 | W38: 2594.5628 | X38: 568.96221 | Y38: 1097.8599 | Z38: 710.73012 | AA38: =AVERAGE(V38,X38:Z38) -> 862.64394 | AB38: =SUM(X38:AA38) -> 3240.1962 | AC38: =AVERAGE(X38:AA38) -> 810.04904 | AD38: =AVERAGE(Y38:AA38,AC38) -> 870.32075 | AE38: =AVERAGE(Z38:AA38,AC38:AD38) -> 813.43596 | AF38: =AVERAGE(AA38,AC38:AE38) -> 839.11242 | AG38: =SUM(AC38:AF38) -> 3332.9182 | AH38: =AVERAGE(AC38:AF38) -> 833.22955 | AI38: =AVERAGE(AD38:AF38,AH38) -> 839.02467 | AJ38: =AVERAGE(AE38:AF38,AH38:AI38) -> 831.20065 | AK38: =AVERAGE(AF38,AH38:AJ38) -> 835.64182 | AL38: =SUM(AH38:AK38) -> 3339.0967 | AM38: =AVERAGE(AH38:AK38) -> 834.77417 | AN38: =AVERAGE(AI38:AK38,AM38) -> 835.16033 | AO38: =AVERAGE(AJ38:AK38,AM38:AN38) -> 834.19424 | AP38: =AVERAGE(AK38,AM38:AO38) -> 834.94264 | AQ38: =SUM(AM38:AP38) -> 3339.0714
B39: Net income | D39: =D37+D38 -> 3931.9655 | E39: =E37+E38 -> 3838.1309 | F39: =F37+F38 -> 3862.0629 | G39: =G37+G38 -> 4315.7928 | H39: =H37+H38 -> 15947.952 | I39: =I37+I38 -> 4996.6463 | J39: =J37+J38 -> 4644.3536 | K39: =K37+K38 -> 4569.5339 | ... U39: =U37+U38 -> 4923.5964 | V39: =W39-SUM(S39:U39) -> 4757.9487 | W39: 20927.446 | X39: =X37+X38 -> 6092.6503 | Y39: =Y37+Y38 -> 6603.7528 | Z39: =Z37+Z38 -> 6051.6147 | AA39: =AA37+AA38 -> 6589.839 | AB39: =AB37+AB38 -> 25337.857 | AC39: =AC37+AC38 -> 7874.3333 | AD39: =AD37+AD38 -> 7658.0094 | AE39: =AE37+AE38 -> 7382.2373 | ... AQ39: =AQ37+AQ38 -> 34841.829 | BD39: 1000000
B40: Basic shares outstanding | D40: 886.45101 | E40: 886.45101 | F40: =(886451010/1000000) -> 886.45101 | G40: =(886451010/1000000) -> 886.45101 | H40: =(D40*D39/H39)+(E40*E39/H39)+(F40*F39/H39)+(G40*G39/H39) -> 886.45101 | I40: =(886451010/1000000) -> 886.45101 | J40: =(886451010/1000000) -> 886.45101 | K40: =(886451010/1000000) -> 886.45101 | L40: 886.45101 | M40: =(I40*I39/M39)+(J40*J39/M39)+(K40*K39/M39)+(L40*L39/M39) -> 886.45101 | N40: =(886451010/1000000) -> 886.45101 | O40: =(886451010/1000000) -> 886.45101 | P40: =(886451010/1000000) -> 886.45101 | Q40: =(886451010/1000000) -> 886.45101 | R40: =(N40*N39/R39)+(O40*O39/R39)+(P40*P39/R39)+(Q40*Q39/R39) -> 886.45101 | S40: =(886451010/1000000) -> 886.45101 | T40: =(886451010/1000000) -> 886.45101 | U40: =Z40 -> 886.45101 | V40: 886 | W40: 886.45101 | X40: =Z40 -> 886.45101 | Y40: 886.45101 | Z40: 886.45101 | AA40: =Z40*(1+AA65)-AA69 -> 886.45101 | AB40: =(X40*X39/AB39)+(Y40*Y39/AB39)+(Z40*Z39/AB39)+AA40*(AA39/AB39) -> 886.45101 | AC40: =AB40*(1+AC65)-AC68 -> 886.45101 | AD40: =AC40*(1+AD65)-AD68 -> 886.45101 | AE40: =AD40*(1+AE65)-AE68 -> 886.45101 | AF40: =AD40*(1+AF65)-AF68 -> 886.45101 | AG40: =(AC40*AC39/AG39)+(AD40*AD39/AG39)+(AE40*AE39/AG39)+(AF40*AF39/AG39) -> 886.45101 | AH40: =AF40*(1+AH65)-AH69 -> 886.45101 | AI40: =AH40*(1+AI65)-AI69 -> 886.45101 | AJ40: =AI40*(1+AJ65)-AJ69 -> 886.45101 | AK40: =AJ40*(1+AK65)-AK69 -> 886.45101 | AL40: =(AH40*AH39/AL39)+(AI40*AI39/AL39)+(AJ40*AJ39/AL39)+(AK40*AK39/AL39) -> 886.45101 | AM40: =AK40*(1+AM65)-AM69 -> 886.45101 | AN40: =AM40*(1+AN65)-AN69 -> 886.45101 | AO40: =AN40*(1+AO65)-AO69 -> 886.45101 | AP40: =AO40*(1+AP65)-AP69 -> 886.45101 | AQ40: =(AM40*AM39/AQ39)+(AN40*AN39/AQ39)+(AO40*AO39/AQ39)+(AP40*AP39/AQ39) -> 886.45101
B41: Diluted shares outstanding | D41: =D40 -> 886.45101 | E41: =E40 -> 886.45101 | F41: =F40 -> 886.45101 | G41: =G40 -> 886.45101 | H41: =(D41*D39/H39)+(E41*E39/H39)+(F41*F39/H39)+(G41*G39/H39) -> 886.45101 | I41: =I40 -> 886.45101 | J41: =J40 -> 886.45101 | K41: =K40 -> 886.45101 | L41: =L40 -> 886.45101 | M41: =(I41*I39/M39)+(J41*J39/M39)+(K41*K39/M39)+(L41*L39/M39) -> 886.45101 | N41: =N40 -> 886.45101 | O41: =O40 -> 886.45101 | P41: =P40 -> 886.45101 | Q41: =Q40 -> 886.45101 | R41: =(N41*N39/R39)+(O41*O39/R39)+(P41*P39/R39)+(Q41*Q39/R39) -> 886.45101 | S41: =S40 -> 886.45101 | T41: =T40 -> 886.45101 | U41: =Z41 -> 886.45101 | V41: 886 | W41: 886.45101 | X41: =Z40 -> 886.45101 | Y41: 886.45101 | Z41: 886.45101 | AA41: =Z41*(1+AA66)-AA69-AA70 -> 886.45101 | AB41: =X41*(X39/AB39)+Y41*(Y39/AB39)+Z41*(Z39/AB39)+AA41*(AA39/AB39) -> 886.45101 | AC41: =AA41*(1+AC66)-AC69-AC70 -> 886.45101 | AD41: =AB41*(1+AD66)-AD69-AD70 -> 886.45101 | AE41: =AC41*(1+AE66)-AE69-AE70 -> 886.45101 | AF41: =AD41*(1+AF66)-AF69-AF70 -> 886.45101 | AG41: =AC41*(AC39/AG39)+AD41*(AD39/AG39)+AE41*(AE39/AG39)+AF41*(AF39/AG39) -> 886.45101 | AH41: =AF41*(1+AH66)-AH69-AH70 -> 886.45101 | AI41: =AG41*(1+AI66)-AI69-AI70 -> 886.45101 | AJ41: =AH41*(1+AJ66)-AJ69-AJ70 -> 886.45101 | AK41: =AI41*(1+AK66)-AK69-AK70 -> 886.45101 | AL41: =AH41*(AH39/AL39)+AI41*(AI39/AL39)+AJ41*(AJ39/AL39)+AK41*(AK39/AL39) -> 886.45101 | AM41: 886.45101 | AN41: 886.45101 | AO41: 886.45101 | AP41: 886.45101 | AQ41: =AM41*(AM39/AQ39)+AN41*(AN39/AQ39)+AO41*(AO39/AQ39)+AP41*(AP39/AQ39) -> 886.45101
B42: Basic EPS | D42: =D39/D40 -> 4.4356264 | E42: =E39/E40 -> 4.3297721 | F42: =F39/F40 -> 4.3567697 | G42: =G39/G40 -> 4.8686196 | H42: =H39/H40 -> 17.990788 | I42: =I39/I40 -> 5.6366863 | J42: =J39/J40 -> 5.2392671 | K42: =K39/K40 -> 5.1548635 | ... AQ42: =AQ39/AQ40 -> 39.304856
B43: Diluted EPS | D43: =D39/D41 -> 4.4356264 | E43: =E39/E41 -> 4.3297721 | F43: =F39/F41 -> 4.3567697 | G43: =G39/G41 -> 4.8686196 | H43: =H39/H41 -> 17.990788 | I43: =I39/I41 -> 5.6366863 | J43: =J39/J41 -> 5.2392671 | K43: =K39/K41 -> 5.1548635 | ... AQ43: =AQ39/AQ41 -> 39.304856
B44: Dividends per share | D44: =D42*33% -> 1.4637567 | E44: =E42*33% -> 1.4288248 | F44: =F42*33% -> 1.437734 | G44: =G42*33% -> 1.6066445 | H44: =5318.70606/H40 -> 6 | I44: =I42*49% -> 2.7619763 | J44: =J42*49% -> 2.5672409 | K44: =K42*49% -> 2.5258831 | L44: =L42*49% -> 2.1815717 | M44: =(8864.5101/M40) -> 10 | N44: =N42*49% -> 3.0403752 | O44: =O42*49% -> 2.8334976 | P44: =P42*49% -> 2.3674263 | Q44: =Q42*49% -> 2.2502135 | R44: =(9307.735605/R40) -> 10.5 | S44: =S42*0.466 -> 3.1544947 | T44: =T42*0.466 -> 2.7573829 | U44: =U42*0.466 -> 2.5882941 | V44: =V42*0.466 -> 2.5024877 | W44: =W42*0.466 -> 11.001386 | X44: =X42*0.46 -> 3.1616176 | Y44: =Y42*0.46 -> 3.4268406 | Z44: =Z42*0.46 -> 3.1403233 | AA44: =AA42*0.42 -> 3.1222621 | AB44: =AB42*0.42 -> 12.005063 | AC44: =AC42*0.42 -> 3.7308548 | AD44: =AD42*0.42 -> 3.6283606 | AE44: =AE42*0.42 -> 3.4977 | AF44: =AF42*0.42 -> 3.0546307 | AG44: =AG42*0.42 -> 13.911546 | AH44: =AH42*0.42 -> 3.9683958 | ... AQ44: =AQ42*0.42 -> 16.508039
B45: Dividend growth rate (YoY) | I45: =I44/D44-1 -> 0.8869094 | J45: =J44/E44-1 -> 0.79674994 | K45: =K44/F44-1 -> 0.75685007 | L45: =L44/G44-1 -> 0.35784348 | M45: =M44/H44-1 -> 0.66666667 | N45: =N44/I44-1 -> 0.10079699 | O45: =O44/J44-1 -> 0.10371317 | P45: =P44/K44-1 -> -0.062733208 | ... AQ45: =AQ44/AL44-1 -> 0.097510296 | BB45: {=#REF!/1000000} -> #REF! | BC45: =$BD$39-BB45 -> #REF!
BC46: =$BD$39-BB46 -> 1000000
B47: Income Statement | D47: Sept-20 | E47: Dec-20 | F47: Mar-21 | G47: Jun-21 | H47: Jun-21 | I47: Sept-21 | J47: Dec-21 | K47: Mar-22 | L47: Jun-22 | M47: Jun-22 | N47: Sept-22 | O47: Dec-22 | P47: Mar-23 | Q47: Jun-23 | R47: Jun-23 | S47: Sept-23 | T47: Dec-23 | U47: Mar-24 | V47: Jun-24 | W47: Jun-24 | X47: Sept-24 | Y47: Dec-24 | Z47: Mar-25 | AA47: Jun-24 | AB47: Jun-24 | AC47: Sept-25 | AD47: Dec-25 | AE47: Mar-26 | AF47: Jun-26 | AG47: Jun-26 | AH47: Sept-26 | AI47: Dec-26 | AJ47: Mar-27 | AK47: Jun-27 | AL47: Jun-27 | AM47: Sept-27 | AN47: Dec-27 | AO47: Mar-28 | AP47: Jun-28 | AQ47: Jun-28
B48: (Taka in millions, except per share data) | D48: 1Q21 | E48: 2Q21 | F48: 3Q21 | G48: 4Q21 | H48: 2021 | I48: 1Q22 | J48: 2Q22 | K48: 3Q22 | L48: 4Q22 | M48: 2022 | N48: 1Q23 | O48: 2Q23 | P48: 3Q23 | Q48: 4Q23 | R48: 2023 | S48: 1Q24 | T48: 2Q24 | U48: 3Q24 | V48: 4Q24 | W48: 2024 | X48: 1Q25 | Y48: 2Q25 | Z48: 3Q25 | AA48: 4Q25 E | AB48: 2025E | AC48: 1Q26E | AD48: 2Q26E | AE48: 3Q26E | AF48: 4Q26E | AG48: 2026E | AH48: 1Q27E | AI48: 2Q27E | AJ48: 3Q27E | AK48: 4Q27E | AL48: 2027E | AM48: 1Q28E | AN48: 2Q28E | AO48: 3Q28E | AP48: 4Q28E | AQ48: 2028E
B49: Revenue growth rate (year over year) | M49: =M17/H17-1 -> 0.1359862 | R49: =R17/M17-1 -> 0.08940843 | W49: =W17/R17-1 -> 0.11718916 | AB49: =AB17/W17-1 -> 0.09211592 | AG49: =AG17/AB17-1 -> 0.13669291 | AL49: =AL17/AG17-1 -> 0.13669291 | AQ49: =AQ17/AL17-1 -> 0.13669291
B50: Revenue growth rate (quarter over quarter) | E50: =E17/D17-1 -> -0.016660965 | F50: =F17/E17-1 -> 0.032675988 | G50: =G17/F17-1 -> 0.017315659 | I50: =I17/G17-1 -> 0.14514418 | J50: =J17/I17-1 -> -0.045808348 | K50: =K17/J17-1 -> 0.032026261 | L50: =L17/K17-1 -> -0.052853204 | N50: =N17/L17-1 -> 0.15811281 | O50: =O17/N17-1 -> 0.0073088565 | P50: =P17/O17-1 -> -0.018515777 | Q50: =Q17/P17-1 -> -0.080803183 | S50: =S17/Q17-1 -> 0.2640159 | T50: =T17/S17-1 -> 0.0032369503 | U50: =U17/T17-1 -> -0.069653059 | V50: =V17/U17-1 -> -0.077498 | X50: =X17/V17-1 -> 0.11658958 | Y50: =Y17/X17-1 -> 0.12531795 | Z50: =Z17/Y17-1 -> 0.0079026697 | AA50: =AA17/Y17-1 -> -0.063038354 | AC50: =AC17/AA17-1 -> 0.17373827 | AD50: =AD17/AC17-1 -> 0.0090771928 | AE50: =AE17/AD17-1 -> -0.0041254725 | AF50: =AF17/AE17-1 -> -0.057061479 | AH50: =AH17/AF17-1 -> 0.19958426 | AI50: =AI17/AH17-1 -> 0.0090771928 | AJ50: =AJ17/AI17-1 -> -0.0041254725 | AK50: =AK17/AJ17-1 -> -0.057061479 | AM50: =AM17/AK17-1 -> 0.19958426 | AN50: =AN17/AM17-1 -> 0.0090771928 | AO50: =AO17/AN17-1 -> -0.0041254725 | AP50: =AP17/AO17-1 -> -0.057061479
B51: Gross margin percentage | D51: =D19/D17 -> 0.51063483 | E51: =E19/E17 -> 0.5343777 | F51: =F19/F17 -> 0.51206562 | G51: =G19/G17 -> 0.48757192 | H51: =H19/H17 -> 0.51087665 | I51: =I19/I17 -> 0.51178768 | J51: =J19/J17 -> 0.53437801 | K51: =K19/K17 -> 0.5136123 | ... AQ51: =AQ19/AQ17 -> 0.49071202
B52: Operating margin | D52: =D25/D17 -> 0.3384081 | E52: =E25/E17 -> 0.34007585 | F52: =F25/F17 -> 0.32294063 | G52: =G25/G17 -> 0.28050951 | H52: =H25/H17 -> 0.32008427 | I52: =I25/I17 -> 0.34764982 | J52: =J25/J17 -> 0.33768364 | K52: =K25/K17 -> 0.32604125 | ... AQ52: =AQ25/AQ17 -> 0.29187213
B53: Net income to revenue | D53: =D39/D17 -> 0.31266671 | E53: =E39/E17 -> 0.31037623 | F53: =F39/F17 -> 0.30242935 | G53: =G39/G17 -> 0.33220751 | H53: =H39/H17 -> 0.31453648 | I53: =I39/I17 -> 0.33586697 | J53: =J39/J17 -> 0.32717368 | K53: =K39/K17 -> 0.31191355 | ... AQ53: =AQ39/AQ17 -> 0.30986916
D54: =D35/D34 -> 0.24589183 | E54: =E35/E34 -> 0.2469364 | F54: =F35/F34 -> 0.22922787 | G54: =G35/G34 -> 0.17030804 | H54: =H35/H34 -> 0.22430247 | I54: =I35/I34 -> 0.21690732 | J54: =J35/J34 -> 0.2224764 | K54: =K35/K34 -> 0.22828176 | ... Z54: =Z35/Z34 -> 0.18006434 | AA54: =22.5% -> 0.225 | AB54: =AA54 -> 0.225 | AC54: =AB54 -> 0.225 | AD54: =AC54 -> 0.225 | AE54: =AD54 -> 0.225 | AF54: =AE54 -> 0.225 | AG54: =AF54 -> 0.225 | AH54: =AG54 -> 0.225 | AI54: =AH54 -> 0.225 | ... AQ54: =AP54 -> 0.225
B55: Finance Cost to Net revenue | D55: =D22/D17 -> 4.2025892e-07 | E55: =E22/E17 -> 0 | F55: =F22/F17 -> 3.0438212e-07 | G55: =G22/G17 -> 3.2875959e-07 | H55: =H22/H17 -> 2.6513209e-07 | I55: =I22/I17 -> 1.4931913e-06 | J55: =J22/J17 -> 4.8959602e-08 | K55: =K22/K17 -> 1.7003411e-07 | ... Z55: =Z22/Z17 -> 0.0024592749 | AA55: =AVERAGE($O$55:$Z$55) -> 0.0030369291 | AB55: =AVERAGE($O$55:$Z$55) -> 0.0030369291 | AC55: =AVERAGE($O$55:$Z$55) -> 0.0030369291 | AD55: =AVERAGE($O$55:$Z$55) -> 0.0030369291 | AE55: =AVERAGE($O$55:$Z$55) -> 0.0030369291 | AF55: =AVERAGE($O$55:$Z$55) -> 0.0030369291 | AG55: =AVERAGE($O$55:$Z$55) -> 0.0030369291 | AH55: =AVERAGE($O$55:$Z$55) -> 0.0030369291 | ... AQ55: =AVERAGE($O$55:$Z$55) -> 0.0030369291
B56: Selling and Distribution Expenses to Net Revenue | D56: =D20/D17 -> 0.15232698 | E56: =E20/E17 -> 0.17074755 | F56: =F20/F17 -> 0.16802402 | G56: =G20/G17 -> 0.18410143 | H56: =H20/H17 -> 0.16891442 | I56: =I20/I17 -> 0.14975808 | J56: =J20/J17 -> 0.17558534 | K56: =K20/K17 -> 0.16678646 | ... Z56: =Z20/Z17 -> 0.19473703 | AA56: =AVERAGE($D$56:$Z$56) -> 0.17684301 | AB56: =AVERAGE($D$56:$Z$56) -> 0.17684301 | AC56: =AVERAGE($D$56:$Z$56) -> 0.17684301 | AD56: =AVERAGE($D$56:$Z$56) -> 0.17684301 | AE56: =AVERAGE($D$56:$Z$56) -> 0.17684301 | AF56: =AVERAGE($D$56:$Z$56) -> 0.17684301 | AG56: =AVERAGE($D$56:$Z$56) -> 0.17684301 | AH56: =AVERAGE($D$56:$Z$56) -> 0.17684301 | ... AQ56: =AVERAGE($D$56:$Z$56) -> 0.17684301
B57: Administrative Expense to Net Revenue | D57: =D21/D17 -> 0.01989933 | E57: =E21/E17 -> 0.024453257 | F57: =F21/F17 -> 0.024801042 | G57: =G21/G17 -> 0.026755144 | H57: =H21/H17 -> 0.024001162 | I57: =I21/I17 -> 0.017781305 | J57: =J21/J17 -> 0.023836705 | K57: =K21/K17 -> 0.023893549 | ... Z57: =Z21/Z17 -> 0.026900664 | AA57: =AVERAGE($D$57:$Z$57) -> 0.02498647 | AB57: =AVERAGE($D$57:$Z$57) -> 0.02498647 | AC57: =AVERAGE($D$57:$Z$57) -> 0.02498647 | AD57: =AVERAGE($D$57:$Z$57) -> 0.02498647 | AE57: =AVERAGE($D$57:$Z$57) -> 0.02498647 | AF57: =AVERAGE($D$57:$Z$57) -> 0.02498647 | AG57: =AVERAGE($D$57:$Z$57) -> 0.02498647 | AH57: =AVERAGE($D$57:$Z$57) -> 0.02498647 | ... AQ57: =AVERAGE($D$57:$Z$57) -> 0.02498647
B58: Value Added Tax to Gross Revenue | D58: =D16/D15 -> 0.14594852 | E58: =E16/E15 -> 0.13853636 | F58: =F16/F15 -> 0.13672246 | G58: =G16/G15 -> 0.10246159 | H58: =H16/H15 -> 0.13099776 | I58: =I16/I15 -> 0.14586884 | J58: =J16/J15 -> 0.13612991 | K58: =K16/K15 -> 0.13217864 | ... X58: =X16/X15 -> 0 | Y58: - | Z58: =Z16/Z15 -> 0 | AA58: =AA16/AA15 -> 0 | AB58: =AB16/AB15 -> 0 | AC58: =AC16/AC15 -> 0 | AD58: =AD16/AD15 -> 0 | AE58: =AE16/AE15 -> 0 | AF58: =AF16/AF15 -> 0 | AG58: =AG16/AG15 -> 0 | ... AQ58: =AQ16/AQ15 -> 0
B59: Effect of Deferred Tax | D59: =D36/D34 -> 0.0031313463 | E59: =E36/E34 -> 5.3018493e-05 | F59: =F36/F34 -> -0.014384592 | G59: =G36/G34 -> 0.051766591 | H59: =H36/H34 -> 0.0093907678 | I59: =I36/I34 -> 0.0015906656 | J59: =J36/J34 -> 0.0034989604 | K59: =K36/K34 -> 0.00064778331 | ... Z59: =Z36/Z34 -> 0.0034316878 | AA59: =AVERAGE(G59,L59,Q59,V59) -> 0.021729975 | AB59: =AVERAGE(H59,M59,R59,W59) -> 0.0072177614 | AC59: =AVERAGE(I59,N59,S59,X59,D59) -> 0.0040449492 | AD59: =AVERAGE(J59,O59,T59,Y59,E59) -> -0.0030861887 | AE59: =AVERAGE(F59,K59,P59,U59,Z59) -> 0.01084376 | AF59: =AVERAGE(L59,Q59,V59,AA59,G59) -> 0.021729975 | AG59: =AVERAGE(M59,R59,W59,AB59,H59) -> 0.0072177614 | AH59: =AVERAGE(N59,S59,X59,AC59,I59,D59) -> 0.0040449492 | AI59: =AVERAGE(O59,T59,Y59,AD59,E59,J59) -> -0.0030861887 | AJ59: =AVERAGE(P59,U59,Z59,AE59,F59) -> 0.012882956 | AK59: =AVERAGE(Q59,V59,AA59,AF59,L59,G59) -> 0.021729975 | AL59: =AVERAGE(R59,W59,AB59,AG59,M59,H59) -> 0.0072177614 | AM59: =AVERAGE(S59,X59,AC59,AH59,D59) -> 0.0046867716 | AN59: =AVERAGE(T59,Y59,AD59,AI59,O59,J59,E59) -> -0.0030861887 | AO59: =AVERAGE(U59,Z59,AE59,AJ59,P59,G59) -> 0.023908153 | AP59: =AVERAGE(V59,AA59,AF59,AK59,Q59,L59,G59) -> 0.021729975 | AQ59: =AVERAGE(W59,AB59,AG59,AL59,R59,M59,H59) -> 0.0072177614
B61: Interest income as a % of investments | E61: =E200/((D82+E82)/2+AVERAGE(D90,E90)) -> 0.15679426 | F61: =F200/((E82+F82)/2+AVERAGE(E90,F90)) -> 0.19118428 | G61: =G200/((F82+G82)/2+AVERAGE(F90,G90)) -> 0.062919113 | I61: =I200/((G82+I82)/2+AVERAGE(G90,I90)) -> 0.14456681 | J61: =J200/((I82+J82)/2+AVERAGE(I90,J90)) -> 0.21281708 | K61: =K200/((J82+K82)/2+AVERAGE(J90,K90)) -> 0.16770825 | L61: =L200/((K82+L82)/2+AVERAGE(K90,L90)) -> 0.12033567 | N61: =N200/((L82+N82)/2+AVERAGE(L90,N90)) -> 0.1613372 | O61: =O200/((N82+O82)/2+AVERAGE(N90,O90)) -> 0.27957058 | P61: =P200/((O82+P82)/2+AVERAGE(O90,P90)) -> 0.20069266 | Q61: =Q200/((P82+Q82)/2+AVERAGE(P90,Q90)) -> 0.23838684 | S61: =S200/((Q82+S82)/2+AVERAGE(Q90,S90)) -> 0.093906714 | T61: =T200/((S82+T82)/2+AVERAGE(S90,T90)) -> 0.16555382 | U61: =U200/((T82+U82)/2+AVERAGE(T90,U90)) -> 0.020204414 | V61: =V200/((U82+V82)/2+AVERAGE(U90,V90)) -> 0.17466316 | X61: =X200/((V82+X82)/2+AVERAGE(V90,X90)) -> 0.12629065 | Y61: =Y200/((X82+Y82)/2+AVERAGE(X90,Y90)) -> 0.14802497 | Z61: =Z200/((Y82+Z82)/2+AVERAGE(Y90,Z90)) -> 0.022414908 | AA61: =AVERAGE(V61,X61:Z61) -> 0.11784842 | AC61: =AVERAGE(X61:AA61) -> 0.10364474 | AD61: =AVERAGE(Y61:AA61,AC61) -> 0.097983258 | AE61: =AVERAGE(Z61:AA61,AC61:AD61) -> 0.085472831 | AF61: =AVERAGE(AA61,AC61:AE61) -> 0.10123731 | AH61: =AVERAGE(AC61:AF61) -> 0.097084534 | AI61: =AVERAGE(AD61:AF61,AH61) -> 0.095444484 | AJ61: =AVERAGE(AE61:AF61,AH61:AI61) -> 0.09480979 | AK61: =AVERAGE(AF61,AH61:AJ61) -> 0.09714403 | AM61: =AVERAGE(AH61:AK61) -> 0.09612071 | AN61: =AVERAGE(AI61:AK61,AM61) -> 0.095879753 | AO61: =AVERAGE(AJ61:AK61,AM61:AN61) -> 0.095988571 | AP61: =AVERAGE(AK61,AM61:AO61) -> 0.096283266
B62: Dividend income as a % of investments | E62: =E27/(((D82+E82)/2)+AVERAGE(D90,E90)) -> 0.01424984 | F62: =F27/(((E82+F82)/2)+AVERAGE(E90,F90)) -> 0.0082059835 | G62: =G27/(((F82+G82)/2)+AVERAGE(F90,G90)) -> 0.057008104 | I62: =I27/(((G82+I82)/2)+AVERAGE(G90,I90)) -> 0.005485646 | J62: =J27/(((I82+J82)/2)+AVERAGE(I90,J90)) -> 0.0021595568 | K62: =K27/(((J82+K82)/2)+AVERAGE(J90,K90)) -> 0.048199621 | L62: =L27/(((K82+L82)/2)+AVERAGE(K90,L90)) -> 0.035486161 | N62: =N27/(((L82+N82)/2)+AVERAGE(L90,N90)) -> 0.0055636185 | O62: =O27/(((N82+O82)/2)+AVERAGE(N90,O90)) -> 0.0054969625 | P62: =P27/(((O82+P82)/2)+AVERAGE(O90,P90)) -> 0.097796232 | Q62: =Q27/(((P82+Q82)/2)+AVERAGE(P90,Q90)) -> 0.016839035 | S62: =S27/(((Q82+S82)/2)+AVERAGE(Q90,S90)) -> 0.0026838766 | T62: =T27/(((S82+T82)/2)+AVERAGE(S90,T90)) -> -2.4568156e-05 | U62: =U27/(((T82+U82)/2)+AVERAGE(T90,U90)) -> 0 | V62: =V27/(((U82+V82)/2)+AVERAGE(U90,V90)) -> 0 | X62: =X27/(((V82+X82)/2)+AVERAGE(V90,X90)) -> 0 | Y62: =Y27/(((X82+Y82)/2)+AVERAGE(X90,Y90)) -> 0 | Z62: =Z27/(((Y82+Z82)/2)+AVERAGE(Y90,Z90)) -> 0 | AA62: =AVERAGE(V62,X62:Z62) -> 0 | AC62: =AVERAGE(X62,Z62:AB62) -> 0 | AD62: =AVERAGE(Y62,AA62:AC62) -> 0 | AE62: =AVERAGE(Z62,AB62:AD62) -> 0 | AF62: =AVERAGE(AA62,AC62:AE62) -> 0 | AH62: =AVERAGE(AC62,AE62:AG62) -> 0 | AI62: =AVERAGE(AD62,AF62:AH62) -> 0 | AJ62: =AVERAGE(AE62,AG62:AI62) -> 0 | AK62: =AVERAGE(AF62,AH62:AJ62) -> 0 | AM62: =AVERAGE(AH62,AJ62:AL62) -> 0 | AN62: =AVERAGE(AI62,AK62:AM62) -> 0 | AO62: =AVERAGE(AJ62,AL62:AN62) -> 0 | AP62: =AVERAGE(AK62,AM62:AO62) -> 0
B63: Interest expense as a percentage of average debt | G63: =G28/((G107+G110)+(F107+F110))/2 -> 0 | I63: =I28/((I107+I110)+(G107+G110))/2 -> 0 | J63: =J28/((J107+J110)+(I107+I110))/2 -> 0 | K63: =K28/((K107+K110)+(J107+J110))/2 -> 0 | L63: =L28/((L107+L110)+(K107+K110))/2 -> 0 | N63: =N28/((N107+N110)+(L107+L110))/2 -> 0 | O63: =O28/((O107+O110)+(N107+N110))/2 -> 0 | P63: =P28/((P107+P110)+(O107+O110))/2 -> 0 | Q63: =Q28/((Q107+Q110)+(P107+P110))/2 -> 0 | S63: =S28/((S107+S110)+(Q107+Q110))/2 -> 0 | T63: =T28/((T107+T110)+(S107+S110))/2 -> 0 | U63: =U28/((U107+U110)+(T107+T110))/2 -> 0 | V63: =V28/((V107+V110)+(U107+U110))/2 -> 0 | X63: =X28/((X107+X110)+(V107+V110))/2 -> 0 | Y63: =Y28/((Y107+Y110)+(X107+X110))/2 -> 0 | Z63: =Z28/((Z107+Z110)+(Y107+Y110))/2 -> 0
B64: Share Count Analysis
B65: Change in basic shares (excluding repurchases) | D65: 0 | E65: 0 | F65: 0 | G65: 0 | H65: 0 | I65: 0 | J65: 0 | K65: 0 | L65: 0 | M65: 0 | N65: 0 | O65: 0 | P65: 0 | Q65: 0 | R65: 0 | S65: 0 | T65: 0 | U65: 0 | V65: 0 | W65: 0 | X65: 0 | Y65: 0 | Z65: 0 | AA65: 0 | AB65: 0 | AC65: 0 | AD65: 0 | AE65: 0 | AF65: 0 | AG65: 0 | AH65: 0 | AI65: 0 | AJ65: 0 | AK65: 0 | AL65: 0 | AM65: 0 | AN65: 0 | AO65: 0 | AP65: 0 | AQ65: 0
B66: Change in diluted shares (excluding repurchases) | D66: 0 | E66: 0 | F66: 0 | G66: 0 | H66: 0 | I66: 0 | J66: 0 | K66: 0 | L66: 0 | M66: 0 | N66: 0 | O66: 0 | P66: 0 | Q66: 0 | R66: 0 | S66: 0 | T66: 0 | U66: 0 | V66: 0 | W66: 0 | X66: 0 | Y66: 0 | Z66: 0 | AA66: 0 | AB66: 0 | AC66: 0 | AD66: 0 | AE66: 0 | AF66: 0 | AG66: 0 | AH66: 0 | AI66: 0 | AJ66: 0 | AK66: 0 | AL66: 0 | AM66: 0 | AN66: 0 | AO66: 0 | AP66: 0 | AQ66: 0
B67: Share repurchase assumptions: average price
B68: Share repurchase: amount in the period ($M)
B69: Shares repurchased (in millions)
B70: Diluted share impact (convertible retirement)
B78: Balance Sheet | D78: Sept-20 | E78: Dec-20 | F78: Mar-21 | G78: Jun-21 | H78: Jun-21 | I78: Sept-21 | J78: Dec-21 | K78: Mar-22 | L78: Jun-22 | M78: Jun-22 | N78: Sept-22 | O78: Dec-22 | P78: Mar-23 | Q78: Jun-23 | R78: Jun-23 | S78: Sept-23 | T78: Dec-23 | U78: Mar-24 | V78: Jun-24 | W78: Jun-24 | X78: Sept-24 | Y78: Dec-24 | Z78: Mar-25 | AA78: Jun-25 | AB78: Jun-25 | AC78: Sept-25 | AD78: Dec-25 | AE78: Mar-26 | AF78: Jun-26 | AG78: Jun-26 | AH78: Sept-26 | AI78: Dec-26 | AJ78: Mar-27 | AK78: Jun-27 | AL78: Jun-27 | AM78: Sept-27 | AN78: Dec-27 | AO78: Mar-28 | AP78: Jun-28 | AQ78: Jun-28
B79: (Taka in millions, except per share data) | D79: 1Q21 | E79: 2Q21 | F79: 3Q21 | G79: 4Q21 | H79: 2021 | I79: 1Q22 | J79: 2Q22 | K79: 3Q22 | L79: 4Q22 | M79: 2022 | N79: 1Q23 | O79: 2Q23 | P79: 3Q23 | Q79: 4Q23 | R79: 2023 | S79: 1Q24 | T79: 2Q24 | U79: 3Q24 | V79: 4Q24 | W79: 2024 | X79: 1Q25 | Y79: 2Q25 | Z79: 3Q25 | AA79: 4Q25 E | AB79: 2025 | AC79: 1Q26 | AD79: 2Q26E | AE79: 3Q26E | AF79: 4Q26E | AG79: 2026E | AH79: 1Q27E | AI79: 2Q27E | AJ79: 3Q27E | AK79: 4Q27E | AL79: 2027E | AM79: 1Q28E | AN79: 2Q28E | AO79: 3Q28E | AP79: 4Q28E | AQ79: 2028E
B80: Assets
B81: Cash and equivalents | D81: 36835 | E81: 40339 | F81: 40482 | G81: 43364 | H81: 43364 | I81: 48312 | J81: 51826 | K81: =48165.147438+22.697218 -> 48187.845 | L81: 48962 | M81: 48962 | N81: 54413 | O81: 55624 | P81: 50491 | Q81: 50094 | R81: 50094 | S81: 56752.061 | T81: 57663.204 | U81: 48400.584 | V81: 52013.46 | W81: 52013.46 | X81: 55288.755 | Y81: 57752.837 | Z81: 50520.972 | AA81: =AA219 -> 60610.84 | AB81: =AB219 -> 60610.84 | AC81: =AC219 -> 49405.757 | AD81: =AD219 -> 72110.996 | AE81: =AE219 -> 65574.493 | AF81: =AF219 -> 75820.367 | AG81: =AG219 -> 75820.367 | AH81: =AH219 -> 58496.886 | ... AQ81: =AQ219 -> 93785.347
B82: Investment in Marketable Securities | H82: =G82 -> 0 | M82: =L82 -> 0 | R82: =Q82 -> 0
B83: Trade and Other Receivables | D83: =1684407750/1000000 -> 1684.4078 | E83: 1687.9698 | F83: 1921.5836 | G83: 2916.1788 | H83: =G83 -> 2916.1788 | I83: =(1592683999/1000000) -> 1592.684 | J83: 2784.6068 | K83: 2802.5513 | L83: 3395.0805 | M83: =L83 -> 3395.0805 | N83: 3843.2308 | O83: 3991.9196 | P83: 3792.6743 | Q83: 6122.2941 | R83: =Q83 -> 6122.2941 | S83: 4923.4682 | T83: 4938.7824 | U83: 4501.2906 | V83: 4503.3862 | W83: 4503.3862 | X83: 5276.9241 | Y83: 4647.2469 | Z83: 7895.2153 | AA83: =(AA17/AA139*2)-Z83 -> 4100.8937 | AB83: =AA83 -> 4100.8937 | AC83: =(AC17/AC139*2)-AA83 -> 9595.3854 | AD83: =(AD17/AD139*2)-AC83 -> 2866.7753 | AE83: =(AE17/AE139*2)-AD83 -> 12695.315 | AF83: =(AF17/AF139*2)-AE83 -> 2402.2078 | AG83: =AF83 -> 2402.2078 | AH83: =(AH17/AH139*2)-AF83 -> 15214.607 | AI83: =(AI17/AI139*2)-AH83 -> 814.82513 | AJ83: =(AJ17/AJ139*2)-AI83 -> 19201.886 | AK83: =(AK17/AK139*2)-AJ83 -> 217.276 | AL83: =AK83 -> 217.276 | AM83: =(AM17/AM139*2)-AK83 -> 22442.321 | AN83: =(AN140/90)*AN17 -> 10308.914 | AO83: =(AO17/AO139*2)-AN83 -> 15437.545 | AP83: =(AP17/AP139*2)-AO83 -> 9540.3179 | AQ83: =AP83 -> 9540.3179
B84: Short Term Loan | D84: =4327076045/1000000 -> 4327.076 | E84: 2743.8296 | F84: 1295.7889 | AA84: -
B85: Inventories | D85: =6361300694/1000000 -> 6361.3007 | E85: 6533.952 | F85: 7225.2143 | G85: 7245.3969 | H85: =G85 -> 7245.3969 | I85: =(6520934488/1000000) -> 6520.9345 | J85: 6471.8567 | K85: 7067.2498 | L85: 8214.1111 | M85: =L85 -> 8214.1111 | N85: 8379.1719 | O85: 9439.0331 | P85: 11264.56 | Q85: 12227.198 | R85: =Q85 -> 12227.198 | S85: 11320.185 | T85: 12260.1 | U85: 13037.309 | V85: 12582.152 | W85: 12582.152 | X85: 14013.883 | Y85: 14592.316 | Z85: 13850.961 | AA85: =(AA18/AA137*2)-Z85 -> 9210.7047 | AB85: =AA85 -> 9210.7047 | AC85: =(AC18/AC137*2)-AB85 -> 19851.104 | AD85: =(AD138/90)*AD18 -> 12790.444 | AE85: =(AE18/AE137*2)-AD85 -> 14461.4 | AF85: =(AF138/90)*AF18 -> 11590.661 | AG85: =AF85 -> 11590.661 | AH85: =(AH18/AH137*2)-AG85 -> 18265.205 | AI85: =(AI138/90)*AI18 -> 13139.918 | AJ85: =(AJ18/AJ137*2)-AI85 -> 14856.53 | AK85: =(AK18/AK137*2)-AJ85 -> 8958.1778 | AL85: =AK85 -> 8958.1778 | AM85: =(AM138/90)*AM18 -> 15335.81 | AN85: =(AN18/AN137*2)-AM85 -> 17781.166 | AO85: =(AO18/AO137*2)-AN85 -> 17499.027 | AP85: =(AP18/AP137*2)-AO85 -> 12511.476 | AQ85: =AP85 -> 12511.476
B86: Deferred tax assets | H86: =G86 -> 0 | M86: =L86 -> 0 | R86: =Q86 -> 0 | AA86: -
B87: Vendor non-trade receivables | H87: =G87 -> 0 | M87: =L87 -> 0 | R87: =Q87 -> 0 | AA87: -
B88: Advances, Deposits and Prepayments | D88: =1849592140/1000000 -> 1849.5921 | E88: 1569.3067 | F88: =(1562632190/1000000) -> 1562.6322 | G88: 1550.765 | H88: =G88 -> 1550.765 | I88: =(2488876983/1000000) -> 2488.877 | J88: 977.67648 | K88: 1132.6771 | L88: 1776.0379 | M88: =L88 -> 1776.0379 | N88: 1516.1083 | O88: 2607.6903 | P88: 1598.0987 | Q88: 2043.3025 | R88: =Q88 -> 2043.3025 | S88: 1806.9578 | T88: 3313.5356 | U88: 2117.4514 | V88: 2106.5228 | W88: 2106.5228 | X88: 2574.1799 | Y88: 1991.0842 | Z88: 1970.4168 | AA88: =Z88*(V88/U88) -> 1960.247 | AB88: =AA88 -> 1960.247 | AC88: =AA88*(X88/V88) -> 2395.4302 | AD88: =AC88*(Y88/X88) -> 1852.8244 | AE88: =AD88*(Z88/Y88) -> 1833.5921 | AF88: =AE88*(AA88/Z88) -> 1824.1286 | AG88: =AF88*(AB88/AA88) -> 1824.1286 | AH88: =AG88*(AC88/AB88) -> 2229.0929 | AI88: =AH88*(AD88/AC88) -> 1724.1653 | AJ88: =AI88*(AE88/AD88) -> 1706.2685 | AK88: =AJ88*(AF88/AE88) -> 1697.4621 | ... AQ88: =AP88*(AL88/AK88) -> 1579.5912
B89: Total Current Assets | D89: =SUM(D81:D88) -> 51057.377 | E89: =SUM(E81:E88) -> 52874.058 | F89: =SUM(F81:F88) -> 52487.219 | G89: =SUM(G81:G88) -> 55076.341 | H89: =SUM(H81:H88) -> 55076.341 | I89: =SUM(I81:I88) -> 58914.495 | J89: =SUM(J81:J88) -> 62060.14 | K89: =SUM(K81:K88) -> 59190.323 | ... AQ89: =SUM(AQ81:AQ88) -> 117416.73
B90: Long-term marketable securities | D90: 3463.1527 | E90: 3605.5013 | F90: =(3339448354/1000000) -> 3339.4484 | G90: 4624.3317 | H90: =G90 -> 4624.3317 | I90: =(4854952895/1000000) -> 4854.9529 | J90: 4254.0541 | K90: 4290.5515 | L90: 4346.7709 | M90: =L90 -> 4346.7709 | N90: 4365.8977 | O90: 4337.3634 | P90: 4432.755 | Q90: 4589.867 | R90: =Q90 -> 4589.867 | S90: 6587.9941 | T90: 8366.73 | U90: 9320.9125 | V90: 9292.4026 | W90: 9292.4026 | X90: 10163.923 | Y90: 9830.5464 | Z90: 9526.596 | AA90: 9569.5 | AB90: =AA90 -> 9569.5 | AC90: 9868.5 | AD90: 8740.5 | AE90: 6976.5 | AF90: 7286.2 | AG90: =AF90 -> 7286.2 | AH90: 7555.5 | AI90: 7853.5 | AJ90: 7459.5 | AK90: 7781.8695 | AL90: =AK90 -> 7781.8695 | AM90: 8013.5 | AN90: 7531.5 | AO90: 7836 | AP90: 8228.2 | AQ90: =AP90 -> 8228.2
B91: Property, plant and equipment, net | D91: 21369.535 | E91: 21697.306 | F91: =(22195604391/1000000) -> 22195.604 | G91: 22884.104 | H91: =G91 -> 22884.104 | I91: =(24308283152/1000000) -> 24308.283 | J91: 25649.652 | K91: 26672.794 | L91: 27182.672 | M91: =L91 -> 27182.672 | N91: 27790.72 | O91: 27941.527 | P91: 27815.02 | Q91: 26058.822 | R91: =Q91 -> 26058.822 | S91: 25870.825 | T91: 25758.949 | U91: 27471.412 | V91: 27750.006 | W91: 27750.006 | X91: 28658.742 | Y91: 30161.061 | Z91: 30816.669 | AA91: =Z91-AA192-AA245 -> 31520.038 | AB91: =AA91 -> 31520.038 | AC91: =AA91-AC192-AC245 -> 32476.217 | AD91: =AB91-AD192-AD245 -> 32467.397 | AE91: =AC91-AE192-AE245 -> 33393.386 | AF91: =AD91-AF192-AF245 -> 33449.175 | AG91: =AF91 -> 33449.175 | AH91: =AF91-AH192-AH245 -> 34529.025 | AI91: =AG91-AI192-AI245 -> 34552.369 | AJ91: =AH91-AJ192-AJ245 -> 35684.794 | AK91: =AI91-AK192-AK245 -> 35764.302 | AL91: =AK91 -> 35764.302 | AM91: =AK91-AM192-AM245 -> 37050.001 | AN91: =AL91-AN192-AN245 -> 37093.946 | AO91: =AM91-AO192-AO245 -> 38453.561 | AP91: =AN91-AP192-AP245 -> 38553.36 | AQ91: =AP91 -> 38553.36
B92: Investment in Associates | D92: 8281.1393 | E92: 8558.4416 | F92: =(8817107224/1000000) -> 8817.1072 | G92: 9277.2472 | H92: =G92 -> 9277.2472 | I92: =(9698004853/1000000) -> 9698.0049 | J92: 10232.022 | K92: 10550.525 | L92: 12874.322 | M92: =L92 -> 12874.322 | N92: 11599.886 | O92: 12116.002 | P92: 12245.631 | Q92: 15076.808 | R92: =Q92 -> 15076.808 | S92: 15436.868 | T92: 16089.427 | U92: 16324.097 | V92: 17397.061 | W92: 17397.061 | X92: 17966.023 | Y92: 19063.883 | Z92: 19482.015 | AA92: =Z92*(Y92/X92) -> 20672.514 | AB92: =AA92 -> 20672.514 | AC92: =AA92*(Z92/Y92) -> 21125.929 | AD92: =AC92*(AA92/Z92) -> 22416.883 | AE92: =AD92*(AC92/AB92) -> 22908.558 | AF92: =AE92*(AD92/AC92) -> 24308.444 | AG92: =AF92 -> 24308.444 | AH92: =AF92*(AE92/AD92) -> 24841.607 | AI92: =AH92*(AF92/AE92) -> 26359.618 | AJ92: =AI92*(AH92/AF92) -> 26937.769 | AK92: =AJ92*(AI92/AH92) -> 28583.871 | AL92: =AK92 -> 28583.871 | AM92: =AK92*(AJ92/AI92) -> 29210.808 | AN92: =AM92*(AK92/AJ92) -> 30995.809 | AO92: =AN92*(AM92/AL92) -> 31675.648 | AP92: =AO92*(AN92/AM92) -> 33611.27 | AQ92: =AP92 -> 33611.27
B93: Pre-Operating Expenses | D93: 0.795074 | E93: 0.898109 | F93: 17.064716 | H93: =G93 -> 0
B94: Acquired intangible assets, net | H94: =G94 -> 0 | M94: =L94 -> 0 | R94: =Q94 -> 0
B95: Long Term Investment - Others | D95: 2744.5881 | E95: 4122.156 | F95: =(4051814428/1000000) -> 4051.8144 | G95: 3590.2003 | H95: =G95 -> 3590.2003 | I95: =(3582927583/1000000) -> 3582.9276 | J95: 4407.0245 | K95: 5104.653 | L95: 5006.3761 | M95: =L95 -> 5006.3761 | N95: 4861.9713 | O95: 6279.2095 | P95: 5740.1909 | Q95: 5603.6919 | R95: =Q95 -> 5603.6919 | S95: 5469.8582 | T95: 7543.2869 | U95: 7014.4442 | V95: 6992.2069 | W95: 6992.2069 | X95: 6950.3615 | Y95: 7532.3096 | Z95: 7591.9281 | AA95: =Z95*(V95/U95) -> 7567.86 | AB95: =AA95 -> 7567.86 | AC95: =AA95*(X95/V95) -> 7522.5696 | AD95: =AC95*(Y95/X95) -> 8152.4282 | AE95: =AD95*(Z95/Y95) -> 8216.9549 | AF95: =AE95*(AA95/Z95) -> 8190.9053 | AG95: =AF95*(AB95/AA95) -> 8190.9053 | AH95: =AG95*(AC95/AA95) -> 8141.8863 | AI95: =AH95*(AD95/AC95) -> 8823.5997 | AJ95: =AI95*(AE95/AD95) -> 8893.4388 | AK95: =AJ95*(AF95/AE95) -> 8865.2446 | AL95: =AK95*(AG95/AF95) -> 8865.2446 | AM95: =AK95*(AH95/AF95) -> 8812.1899 | AN95: =AM95*(AI95/AH95) -> 9550.0274 | AO95: =AN95*(AJ95/AI95) -> 9625.6161 | AP95: =AO95*(AK95/AJ95) -> 9595.1008 | AQ95: =AP95*(AL95/AK95) -> 9595.1008
B96: Total Assets | D96: =SUM(D89:D95) -> 86916.587 | E96: =SUM(E89:E95) -> 90858.362 | F96: =SUM(F89:F95) -> 90908.258 | G96: =SUM(G89:G95) -> 95452.224 | H96: =SUM(H89:H95) -> 95452.224 | I96: =SUM(I89:I95) -> 101358.66 | J96: =SUM(J89:J95) -> 106602.89 | K96: =SUM(K89:K95) -> 105808.85 | ... AQ96: =SUM(AQ89:AQ95) -> 207404.66
B98: Liabilities
B99: Trade Payables | D99: 573.25651 | E99: 491.58503 | F99: =(406106816/1000000) -> 406.10682 | G99: 666.1672 | H99: =G99 -> 666.1672 | I99: =(720380164/1000000) -> 720.38016 | J99: 788.97588 | K99: 855.26687 | L99: 625.98491 | M99: =L99 -> 625.98491 | N99: 880.078 | O99: 1279.4311 | P99: 1100.0275 | Q99: 1001.7588 | R99: =Q99 -> 1001.7588 | S99: 1065.6985 | T99: 3383.4377 | U99: 800.52994 | V99: 1455.4283 | W99: 1455.4283 | X99: 1532.3647 | Y99: 1325.421 | Z99: 1260.5371 | AA99: =AA18*Workings!$K$78 -> 1442.0161 | AB99: =AA99 -> 1442.0161 | AC99: =AC18*Workings!$K$78 -> 1475.4781 | AD99: =AD18*Workings!$K$78 -> 1513.3795 | AE99: =AE18*Workings!$K$78 -> 1531.5431 | AF99: =AF18*Workings!$K$78 -> 1603.8131 | AG99: =AF99 -> 1603.8131 | AH99: =AH18*Workings!$K$78 -> 1677.1655 | AI99: =AI18*Workings!$K$78 -> 1720.2477 | AJ99: =AJ18*Workings!$K$78 -> 1740.8942 | AK99: =AK18*Workings!$K$78 -> 1823.043 | AL99: =AK99 -> 1823.043 | AM99: =AM18*Workings!$K$78 -> 1906.4221 | AN99: =AN18*Workings!$K$78 -> 1955.3934 | AO99: =AO18*Workings!$K$78 -> 1978.8621 | AP99: =AP18*Workings!$K$78 -> 2072.2401 | AQ99: =AP99 -> 2072.2401
B100: Other Payables | D100: 1516.9872 | E100: 5331.6957 | F100: 2575.5315 | G100: 1381.5018 | H100: =G100 -> 1381.5018 | I100: =(2664310046/1000000) -> 2664.31 | J100: 1379.892 | K100: 1451.492 | L100: 1613.9009 | M100: =L100 -> 1613.9009 | N100: 2245.3931 | O100: 1986.7739 | P100: 2222.7492 | Q100: 1877.9623 | R100: =Q100 -> 1877.9623 | S100: 1908.0979 | T100: 1886.5763 | U100: 1705.4964 | V100: 1820.944 | W100: 1820.944 | X100: 3013.9474 | Y100: 11822.936 | Z100: 2167.4112 | AA100: =(AA18/AA150*2)-Z100 -> 1221.1944 | AB100: =AA100 -> 1221.1944 | AC100: =(AC18/AC150*2)-AB100 -> 3026.9191 | AD100: =(AD151/90)*AD18 -> 7081.6087 | AE100: =(AE151/90)*AE18 -> 7154.4878 | AF100: =(AF151/90)*AF18 -> 1818.0356 | AG100: =AF100 -> 1818.0356 | AH100: =(AH151/90)*AH18 -> 565.24439 | AI100: =(AI151/90)*AI18 -> 1884.5257 | AJ100: =(AJ18/AJ150*2)-AI100 -> 1923.3142 | AK100: =(AK151/90)*AK18 -> 483.80741 | AL100: =AK100 -> 483.80741 | AM100: =(AM151/90)*AM18 -> 150.42028 | AN100: =(AN18/AN150*2)-AM100 -> 852.58264 | AO100: =(AO18/AO150*2)-AN100 -> 160.7425 | AP100: =(AP18/AP150*2)-AO100 -> 96.754781 | AQ100: =AP100 -> 96.754781
B101: Dividends Payable | J101: =5318.70606 -> 5318.7061 | O101: =8864.5101 -> 8864.5101 | T101: =9307.735605 -> 9307.7356
B102: Long Term Loan - Current Portion | H102: =G102 -> 0 | I102: =(7859740/1000000) -> 7.85974 | J102: 21.409635 | K102: 134.05633 | L102: 200 | M102: =L102 -> 200 | N102: 300 | O102: 443.63405 | P102: 440.95007 | Q102: 618.60947 | R102: =Q102 -> 618.60947 | S102: 576.32516 | T102: 566.22409 | U102: 599.11568 | V102: 614.53983 | W102: 614.53983 | X102: 698.72988 | Y102: 620.43958 | Z102: 622.23563 | AA102: =AA127*AA147*AA152 -> 693.98086 | AB102: =AA102 -> 693.98086 | AC102: =AC127*AC147*AC152 -> 713.99361 | AD102: =AD127*AD147*AD152 -> 724.37204 | AE102: =AE127*AE147*AE152 -> 749.08205 | AF102: =AF127*AF147*AF152 -> 775.11538 | AG102: =AF102 -> 775.11538 | AH102: =AH127*AH147*AH152 -> 797.65672 | AI102: =AI127*AI147*AI152 -> 821.02599 | AJ102: =AJ127*AJ147*AJ152 -> 846.80101 | AK102: =AK127*AK147*AK152 -> 868.27138 | AL102: =AK102 -> 868.27138 | AM102: =AM127*AM147*AM152 -> 895.40482 | AN102: =AN127*AN147*AN152 -> 922.90149 | AO102: =AO127*AO147*AO152 -> 949.87527 | AP102: =AP127*AP147*AP152 -> 972.31834 | AQ102: =AP102 -> 972.31834
B103: Unclaimed Dividend | D103: 333.57655 | E103: 332.15832 | F103: 329.32695 | G103: 375.16574 | H103: =G103 -> 375.16574 | I103: =(103405665/1000000) -> 103.40566 | J103: 99.408216 | K103: 74.251093 | L103: 129.63603 | M103: =L103 -> 129.63603 | N103: 127.25006 | O103: 125.82968 | P103: 124.24712 | Q103: 158.99779 | R103: =Q103 -> 158.99779 | S103: 151.99028 | T103: 150.48965 | U103: 241.49135 | V103: 191.98363 | W103: 191.98363 | X103: 188.63772 | Y103: 186.11177 | Z103: 184.77745 | AA103: =Z103*(1+Workings!F79) -> 229.11411 | AB103: =AA103 -> 229.11411 | AC103: =AA103*(1+Workings!C79) -> 169.02118 | AD103: =AC103*(1+Workings!D79) -> 166.31917 | AE103: =AD103*(1+Workings!E79) -> 180.06271 | AF103: =AE103*(1+Workings!F79) -> 223.26808 | AG103: =AF103 -> 223.26808 | AH103: =AF103*(1+Workings!C79) -> 164.70847 | AI103: =AH103*(1+Workings!D79) -> 162.07541 | AJ103: =AI103*(1+Workings!E79) -> 175.46827 | AK103: =AJ103*(1+Workings!F79) -> 217.57122 | AL103: =AK103 -> 217.57122 | AM103: =AK103*(1+Workings!C79) -> 160.50581 | AN103: =AM103*(1+Workings!D79) -> 157.93993 | AO103: =AN103*(1+Workings!E79) -> 170.99106 | AP103: =AO103*(1+Workings!F79) -> 212.01972 | AQ103: =AP103 -> 212.01972
B104: Current Tax Liabilities | D104: 1208.7007 | E104: 1387.5936 | F104: 738.72918 | G104: 572.67507 | H104: =G104 -> 572.67507 | J104: 1085.2645 | K104: 698.53649 | L104: 911.50487 | M104: =L104 -> 911.50487 | N104: 1452.9422 | O104: 1762.7465 | P104: 1361.9661 | Q104: 356.09555 | R104: =Q104 -> 356.09555 | S104: 929.46357 | T104: 1045.4658 | U104: 1229.2151 | V104: 912.2659 | W104: 912.2659 | X104: 1079.9484 | Y104: 1274.9544 | Z104: 1637.1087 | AA104: =Z104*(1+Workings!F89) -> 1259.7487 | AB104: =AA104 -> 1259.7487 | AC104: =AA104*(1+Workings!C89) -> 1696.8704 | AD104: =AC104*(1+Workings!D89) -> 1979.656 | AE104: =AD104*(1+Workings!E89) -> 1918.3387 | AF104: =AE104*(1+Workings!F89) -> 1476.1541 | AG104: =AF104 -> 1476.1541 | AH104: =AF104*(1+Workings!C89) -> 1988.3665 | AI104: =AH104*(1+Workings!D89) -> 2319.7304 | AJ104: =AI104*(1+Workings!E89) -> 2247.8797 | AK104: =AJ104*(1+Workings!F89) -> 1729.7346 | AL104: =AK104 -> 1729.7346 | AM104: =AK104*(1+Workings!C89) -> 2329.9372 | AN104: =AM104*(1+Workings!D89) -> 2718.2242 | AO104: =AN104*(1+Workings!E89) -> 2634.0308 | AP104: =AO104*(1+Workings!F89) -> 2026.8763 | AQ104: =AP104 -> 2026.8763
B105: Accrued expenses | D105: 25.565021 | E105: 57.044854 | F105: =(63649283/1000000) -> 63.649283 | G105: 183.04908 | H105: =G105 -> 183.04908 | I105: =(87724276/1000000) -> 87.724276 | J105: 107.84238 | K105: 90.311984 | L105: 180.80211 | M105: =L105 -> 180.80211 | N105: 43.847371 | O105: 106.67132 | P105: 180.13052 | Q105: 215.72173 | R105: =Q105 -> 215.72173 | S105: 82.113227 | T105: 366.48474 | U105: 152.29802 | V105: 286.79327 | W105: 286.79327 | X105: 246.7854 | Y105: 261.22667 | Z105: 254.81636 | AA105: =Z105*(V105/U105) -> 479.84614 | AB105: =AA105 -> 479.84614 | AC105: =AB105*(X105/W105) -> 412.90725 | AD105: =AC105*(Y105/X105) -> 437.06955 | AE105: =AD105*(Z105/Y105) -> 426.3442 | AF105: =AE105*(AA105/Z105) -> 802.85118 | AG105: =AF105*(AB105/AA105) -> 802.85118 | AH105: =AG105*(AC105/AB105) -> 690.85285 | AI105: =AH105*(AD105/AC105) -> 731.27983 | AJ105: =AI105*(AE105/AD105) -> 713.33478 | ... AQ105: =AP105*(AL105/AK105) -> 2247.5074
B106: Deferred revenue (current portion) | H106: =G106 -> 0 | M106: =L106 -> 0 | R106: =Q106 -> 0
B107: Commercial paper/current portion of LT debt
B108: Total Current liabilities | D108: =SUM(D99:D107) -> 3658.0859 | E108: =SUM(E99:E107) -> 7600.0775 | F108: =SUM(F99:F107) -> 4113.3438 | G108: =SUM(G99:G107) -> 3178.5589 | H108: =SUM(H99:H107) -> 3178.5589 | I108: =SUM(I99:I107) -> 3583.6799 | J108: =SUM(J99:J107) -> 8801.4987 | K108: =SUM(K99:K107) -> 3303.9147 | ... AQ108: =SUM(AQ99:AQ107) -> 7627.7166
B109: Deferred revenue (non-current) | H109: =G109 -> 0 | M109: =L109 -> 0 | R109: =Q109 -> 0
B110: Long Term Loan | G110: 103.70747 | H110: =G110 -> 103.70747 | I110: =(142963721/1000000) -> 142.96372 | J110: 1439.6069 | K110: 1691.333 | L110: 1714.2702 | M110: =L110 -> 1714.2702 | N110: 1685.9558 | O110: 1553.0391 | P110: 1471.9521 | Q110: 1368.3569 | R110: =Q110 -> 1368.3569 | S110: 1208.569 | T110: 1049.3361 | U110: 948.8946 | V110: 814.53983 | W110: 814.53983 | X110: 665.45367 | Y110: 510.21979 | Z110: 355.55891 | AA110: =AA127*AA147*(1-AA152) -> 610.90584 | AB110: =AA110 -> 610.90584 | AC110: =AC127*AC147*(1-AC152) -> 567.20854 | AD110: =AD127*AD147*(1-AD152) -> 549.68359 | AE110: =AE127*AE147*(1-AE152) -> 557.05457 | AF110: =AF127*AF147*(1-AF152) -> 614.48945 | AG110: =AF110 -> 614.48945 | AH110: =AH127*AH147*(1-AH152) -> 615.91054 | AI110: =AI127*AI147*(1-AI152) -> 629.45536 | AJ110: =AJ127*AJ147*(1-AJ152) -> 650.88262 | AK110: =AK127*AK147*(1-AK152) -> 672.90702 | AL110: =AK110 -> 672.90702 | AM110: =AM127*AM147*(1-AM152) -> 690.00548 | AN110: =AN127*AN147*(1-AN152) -> 710.83909 | AO110: =AO127*AO147*(1-AO152) -> 732.4607 | AP110: =AP127*AP147*(1-AP152) -> 750.36962 | AQ110: =AP110 -> 750.36962
B111: Deferred Tax Liabilities | D111: 1257.3327 | E111: 1288.7828 | F111: =(1317037391/1000000) -> 1317.0374 | G111: 1274.853 | H111: =G111 -> 1274.853 | I111: =(1269210785/1000000) -> 1269.2108 | J111: 1195.1001 | K111: 1181.4918 | L111: 1178.7403 | M111: =L111 -> 1178.7403 | N111: 1144.5391 | O111: 1141.0454 | P111: 1149.0481 | Q111: 1022.1538 | R111: =Q111 -> 1022.1538 | S111: 987.01764 | T111: 1104.4247 | U111: 721.38669 | V111: 619.08152 | W111: 619.08152 | X111: 706.55479 | Y111: 569.08614 | Z111: 481.74314 | AA111: =Z111+AA36 -> 637.94639 | AB111: =AA111 -> 637.94639 | AC111: =AB111+AC36 -> 674.62549 | AD111: =AC111+AD36 -> 647.48763 | AE111: =AD111+AE36 -> 738.1297 | AF111: =AE111+AF36 -> 891.08159 | AG111: =AF111 -> 891.08159 | AH111: =AG111+AH36 -> 930.24345 | AI111: =AH111+AI36 -> 900.70177 | AJ111: =AI111+AJ36 -> 1020.668 | AK111: =AJ111+AK36 -> 1188.1023 | AL111: =AK111 -> 1188.1023 | AM111: =AL111+AM36 -> 1238.3891 | AN111: =AM111+AN36 -> 1205.8547 | AO111: =AN111+AO36 -> 1452.574 | AP111: =AO111+AP36 -> 1636.8185 | AQ111: =AP111 -> 1636.8185
B112: Total Non current liabilities | D112: =SUM(D109:D111) -> 1257.3327 | E112: =SUM(E109:E111) -> 1288.7828 | F112: =SUM(F109:F111) -> 1317.0374 | G112: =SUM(G109:G111) -> 1378.5605 | H112: =SUM(H109:H111) -> 1378.5605 | I112: =SUM(I109:I111) -> 1412.1745 | J112: =SUM(J109:J111) -> 2634.707 | K112: =SUM(K109:K111) -> 2872.8248 | ... AQ112: =SUM(AQ109:AQ111) -> 2387.1881
B113: Total liabilities | D113: =D108+D112 -> 4915.4186 | E113: =E108+E112 -> 8888.8603 | F113: =F108+F112 -> 5430.3812 | G113: =G108+G112 -> 4557.1194 | H113: =H108+H112 -> 4557.1194 | I113: =I108+I112 -> 4995.8544 | J113: =J108+J112 -> 11436.206 | K113: =K108+K112 -> 6176.7396 | ... AQ113: =AQ108+AQ112 -> 10014.905
...

Sheet Beta 
B5: Date | C5: Price (Million) | D5: Market Return | E5: Stock Price | F5: Return of Square
B6: 45870 | C6: 5350.25 | D6: =(C6/C7)-1 -> -0.017116078 | E6: 232.2 | F6: =(E6/E7)-1 -> 0.010443864
B7: 45839 | C7: 5443.42 | D7: =(C7/C8)-1 -> 0.12504779 | E7: 229.8 | F7: =(E7/E8)-1 -> 0.10004787
B8: 45809 | C8: 4838.39 | D8: =(C8/C9)-1 -> 0.043224118 | E8: 208.9 | F8: =(E8/E9)-1 -> 0.034670629 | J8: SUMMARY OUTPUT
B9: 45778 | C9: 4637.92 | D9: =(C9/C10)-1 -> -0.056934639 | E9: 201.9 | F9: =(E9/E10)-1 -> -0.056982718
B10: 45748 | C10: 4917.92 | D10: =(C10/C11)-1 -> -0.0577181 | E10: 214.1 | F10: =(E10/E11)-1 -> -0.027260336 | J10: Regression Statistics
B11: 45717 | C11: 5219.16 | D11: =(C11/C12)-1 -> -0.005362758 | E11: 220.1 | F11: =(E11/E12)-1 -> 0.016628176 | J11: Multiple R | K11: 0.77203139
B12: 45689 | C12: 5247.3 | D12: =(C12/C13)-1 -> 0.026286452 | E12: 216.5 | F12: =(E12/E13)-1 -> -0.00092293493 | J12: R Square | K12: 0.59603247
B13: 45658 | C13: 5112.9 | D13: =(C13/C14)-1 -> -0.019848786 | E13: 216.7 | F13: =(E13/E14)-1 -> -0.0045934773 | J13: Adjusted R Square | K13: 0.5864142
B14: 45627 | C14: 5216.44 | D14: =(C14/C15)-1 -> 0.0045930836 | E14: 217.7 | F14: =(E14/E15)-1 -> 0.0441247 | J14: Standard Error | K14: 0.019132195
B15: 45597 | C15: 5192.59 | D15: =(C15/C16)-1 -> -0.0013097665 | E15: 208.5 | F15: =(E15/E16)-1 -> -0.043139055 | J15: Observations | K15: 44
B16: 45566 | C16: 5199.4 | D16: =(C16/C17)-1 -> -0.075580052 | E16: 217.9 | F16: =(E16/E17)-1 -> -0.04930192
B17: 45536 | C17: 5624.5 | D17: =(C17/C18)-1 -> -0.030997068 | E17: 229.2 | F17: =(E17/E18)-1 -> -0.018415418 | J17: ANOVA
B18: 45505 | C18: 5804.42 | D18: =(C18/C19)-1 -> 0.099224122 | E18: 233.5 | F18: =(E18/E19)-1 -> 0.096244131 | K18: df | L18: SS | M18: MS | N18: F | O18: Significance F
B19: 45474 | C19: 5280.47 | D19: =(C19/C20)-1 -> -0.0089951956 | E19: 213 | F19: =(E19/E20)-1 -> 0.0099573257 | J19: Regression | K19: 1 | L19: 0.022683096 | M19: 0.022683096 | N19: 61.968752 | O19: 8.4510429e-10
B20: 45444 | C20: 5328.4 | D20: =(C20/C21)-1 -> 0.014554566 | E20: 210.9 | F20: =(E20/E21)-1 -> 0.011510791 | J20: Residual | K20: 42 | L20: 0.015373717 | M20: 0.00036604087
B21: 45413 | C21: 5251.96 | D21: =(C21/C22)-1 -> -0.05957222 | E21: 208.5 | F21: =(E21/E22)-1 -> -0.011379801 | J21: Total | K21: 43 | L21: 0.038056813
B22: 45383 | C22: 5584.65 | D22: =(C22/C23)-1 -> -0.042034753 | E22: 210.9 | F22: =(E22/E23)-1 -> -0.031235645
B23: 45352 | C23: 5829.7 | D23: =(C23/C24)-1 -> -0.067925059 | E23: 217.7 | F23: =(E23/E24)-1 -> 0.0041512915 | K23: Coefficients | L23: Standard Error | M23: t Stat | N23: P-value | O23: Lower 95% | P23: Upper 95% | Q23: Lower 95.0% | R23: Upper 95.0%
B24: 45323 | C24: 6254.54 | D24: =(C24/C25)-1 -> 0.016446353 | E24: 216.8 | F24: =(E24/E25)-1 -> -0.0055045872 | J24: Intercept | K24: 0.0050595959 | L24: 0.0029063269 | M24: 1.7408902 | N24: 0.089024916 | O24: -0.0008056092 | P24: 0.010924801 | Q24: -0.0008056092 | R24: 0.010924801
B25: 45292 | C25: 6153.34 | D25: =(C25/C26)-1 -> -0.014913952 | E25: 218 | F25: =(E25/E26)-1 -> 0.03661436 | J25: Market Return | K25: 0.60999199 | L25: 0.077488589 | M25: 7.8720234 | N25: 8.4510429e-10 | O25: 0.45361368 | P25: 0.76637029 | Q25: 0.45361368 | R25: 0.76637029
B26: 45261 | C26: 6246.5 | D26: =(C26/C27)-1 -> 0.0037714747 | E26: 210.3 | F26: =(E26/E27)-1 -> 0.0023832221
B27: 45231 | C27: 6223.03 | D27: =(C27/C28)-1 -> -0.0089138398 | E27: 209.8 | F27: =(E27/E28)-1 -> -0.0061582189
B28: 45200 | C28: 6279 | D28: =(C28/C29)-1 -> -0.00089583635 | E28: 211.1 | F28: =(E28/E29)-1 -> 0.0061963775
B29: 45170 | C29: 6284.63 | D29: =(C29/C30)-1 -> -0.0023605048 | E29: 209.8 | F29: =(E29/E30)-1 -> -0.0061582189
B30: 45139 | C30: 6299.5 | D30: =(C30/C31)-1 -> -0.0040017012 | E30: 211.1 | F30: =(E30/E31)-1 -> 0.0061963775
B31: 45108 | C31: 6324.81 | D31: =(C31/C32)-1 -> -0.0030390489 | E31: 209.8 | F31: =(E31/E32)-1 -> 0
B32: 45078 | C32: 6344.09 | D32: =(C32/C33)-1 -> 0.00068614801 | E32: 209.8 | F32: =(E32/E33)-1 -> 0
B33: 45047 | C33: 6339.74 | D33: =(C33/C34)-1 -> 0.01230302 | E33: 209.8 | F33: =(E33/E34)-1 -> 0
B34: 45017 | C34: 6262.69 | D34: =(C34/C35)-1 -> 0.0090046401 | E34: 209.8 | F34: =(E34/E35)-1 -> 0
B35: 44986 | C35: 6206.8 | D35: =(C35/C36)-1 -> -0.0016326334 | E35: 209.8 | F35: =(E35/E36)-1 -> 0
B36: 44958 | C36: 6216.95 | D36: =(C36/C37)-1 -> -0.0079941918 | E36: 209.8 | F36: =(E36/E37)-1 -> 0
B37: 44927 | C37: 6267.05 | D37: =(C37/C38)-1 -> 0.0097054687 | E37: 209.8 | F37: =(E37/E38)-1 -> 0
... B49: 44562 | C49: 6926.29 | D49: =(C49/C50)-1 -> 0.025107117 | E49: 220.2 | F49: =(E49/E50)-1 -> 0.027531498
B50: 44531 | C50: 6756.65 | D50: =(C50/#REF!)-1 -> #REF! | E50: 214.3 | F50: =(E50/#REF!)-1 -> #REF!

Sheet SR & Volatility workings
A2: Date | B2: Price (Million) | C2: Market Return | D2: Stock Price | E2: Return of Square | F2: Ex.R
A3: 45870 | B3: 5350.25 | C3: =(B3/B4)-1 -> -0.017116078 | D3: 232.2 | E3: =(D3/D4)-1 -> 0.010443864 | F3: =E3-C3 -> 0.027559942
A4: 45839 | B4: 5443.42 | C4: =(B4/B5)-1 -> 0.12504779 | D4: 229.8 | E4: =(D4/D5)-1 -> 0.10004787 | F4: =E4-C4 -> -0.024999925
A5: 45809 | B5: 4838.39 | C5: =(B5/B6)-1 -> 0.043224118 | D5: 208.9 | E5: =(D5/D6)-1 -> 0.034670629 | F5: =E5-C5 -> -0.0085534887
A6: 45778 | B6: 4637.92 | C6: =(B6/B7)-1 -> -0.056934639 | D6: 201.9 | E6: =(D6/D7)-1 -> -0.056982718 | F6: =E6-C6 -> -4.8079322e-05
A7: 45748 | B7: 4917.92 | C7: =(B7/B8)-1 -> -0.0577181 | D7: 214.1 | E7: =(D7/D8)-1 -> -0.027260336 | F7: =E7-C7 -> 0.030457764
A8: 45717 | B8: 5219.16 | C8: =(B8/B9)-1 -> -0.005362758 | D8: 220.1 | E8: =(D8/D9)-1 -> 0.016628176 | F8: =E8-C8 -> 0.021990934
A9: 45689 | B9: 5247.3 | C9: =(B9/B10)-1 -> 0.026286452 | D9: 216.5 | E9: =(D9/D10)-1 -> -0.00092293493 | F9: =E9-C9 -> -0.027209387
A10: 45658 | B10: 5112.9 | C10: =(B10/B11)-1 -> -0.019848786 | D10: 216.7 | E10: =(D10/D11)-1 -> -0.0045934773 | F10: =E10-C10 -> 0.015255308
A11: 45627 | B11: 5216.44 | C11: =(B11/B12)-1 -> 0.0045930836 | D11: 217.7 | E11: =(D11/D12)-1 -> 0.0441247 | F11: =E11-C11 -> 0.039531617
A12: 45597 | B12: 5192.59 | C12: =(B12/B13)-1 -> -0.0013097665 | D12: 208.5 | E12: =(D12/D13)-1 -> -0.043139055 | F12: =E12-C12 -> -0.041829288
A13: 45566 | B13: 5199.4 | C13: =(B13/B14)-1 -> -0.075580052 | D13: 217.9 | E13: =(D13/D14)-1 -> -0.04930192 | F13: =E13-C13 -> 0.026278132
A14: 45536 | B14: 5624.5 | C14: =(B14/B15)-1 -> -0.030997068 | D14: 229.2 | E14: =(D14/D15)-1 -> -0.018415418 | F14: =E14-C14 -> 0.01258165
... A46: 44562 | B46: 6926.29 | C46: =(B46/B47)-1 -> 0.025107117 | D46: 220.2 | E46: =(D46/D47)-1 -> 0.027531498 | F46: =E46-C46 -> 0.0024243812
A47: 44531 | B47: 6756.65 | C47: =(B47/#REF!)-1 -> #REF! | D47: 214.3 | E47: =(D47/#REF!)-1 -> #REF! | F47: =E47-C47 -> #REF!
D49: Vol | E49: =_xlfn.STDEV.S(E3:E46) -> 0.029749658 | G49: Sharpe Ratio | H49: =E50/E51 -> 0.093870086
D50: Avg. | E50: =AVERAGE(E3:E46) -> 0.0022473408 | G50: Volatility | H50: =SQRT(252)*E49 -> 0.47226118
D51: Std. of Ex.R | E51: =STDEV(F3:F46) -> 0.023940968

Sheet DDM
B3: Terminal Growth | C3: ='Sensitivity Analysis'!C7 -> 0.057873759
B4: Required return on equity | C4: ='SQURPHARMA Earnings Model T-1'!C270 -> 0.13164168
B6: DDM Valuation | C6: Projected Year 1 | D6: Projected Year 2 | E6: Projected Year 3 | F6: Projected Year 4
C7: June | D7: June | E7: June | F7: June
C8: 2025E | D8: 2026E | E8: 2027E | F8: 2028E
B9: No. of shares outstanding | C9: ='SQURPHARMA Earnings Model T-1'!AB41 -> 886.45101 | D9: ='SQURPHARMA Earnings Model T-1'!AC41 -> 886.45101 | E9: ='SQURPHARMA Earnings Model T-1'!AD41 -> 886.45101 | F9: ='SQURPHARMA Earnings Model T-1'!AE41 -> 886.45101
B10: Dividend | C10: =C9*'SQURPHARMA Earnings Model T-1'!AB44 -> 10641.9 | D10: =D9*'SQURPHARMA Earnings Model T-1'!AG44 -> 12331.904 | E10: =E9*'SQURPHARMA Earnings Model T-1'!AL44 -> 13333.422 | F10: =F9*'SQURPHARMA Earnings Model T-1'!AQ44 -> 14633.568
B11: Projected Years | C11: 0.25 | D11: 1.25 | E11: 2.25 | F11: 3.25
B12: PV of DIvidend | C12: =C10/((1+$C$4)^C$11) -> 10317.915 | D12: =D10/((1+$C$4)^D$11) -> 10565.595 | E12: =E10/((1+$C$4)^E$11) -> 10094.772 | F12: =F10/((1+$C$4)^F$11) -> 9790.3046
B13: Total PV of Dividend | C13: =SUM(C12:F12) -> 40768.587
B14: Continuing Value | C14: =F10*(1+C3)/(C4-C3) -> 209853.67
B15: PV of Terminal Value | C15: =C14/((1+C4)^F11) -> 140398.52
B16: Equity Value | C16: =C15+C13 -> 181167.11
B17: Number of Shares Outstanding | C17: ='SQURPHARMA Earnings Model T-1'!Z40 -> 886.45101
B18: Equity Value per share (Fair Value) | C18: =C16/C17 -> 204.37351

Sheet PE
A1: Last 12 Month P/E Ratio
A2: Date | B2: Price | C2: EPS | D2: P/E
A3: 45743 | B3: 220.1 | C3: 23.6081 | D3: =B3/$C$3 -> 9.3230713
A4: 45741 | B4: 219.7 | D4: =B4/$C$3 -> 9.306128 | F4: Average P/E | G4: =AVERAGE(D3:D237) -> 9.4368104
A5: 45740 | B5: 220 | D5: =B5/$C$3 -> 9.3188355 | F5: Maximum P/E | G5: =LARGE(D3:D237,1) -> 10.190881
A6: 45739 | B6: 219.6 | D6: =B6/$C$3 -> 9.3018921 | F6: Minimum P/E | G6: =SMALL(D3:D237,1) -> 8.8105354
A7: 45736 | B7: 220.1 | D7: =B7/$C$3 -> 9.3230713
A8: 45735 | B8: 220.4 | D8: =B8/$C$3 -> 9.3357788
A9: 45734 | B9: 220.6 | D9: =B9/$C$3 -> 9.3442505
A10: 45733 | B10: 219.9 | D10: =B10/$C$3 -> 9.3145997 | I10: Relative Valuation:
A11: 45732 | B11: 220.4 | D11: =B11/$C$3 -> 9.3357788
A12: 45729 | B12: 219.9 | D12: =B12/$C$3 -> 9.3145997 | I12: Particular | J12: Multiple | K12: EPS | L12: Valuation
A13: 45728 | B13: 218.9 | D13: =B13/$C$3 -> 9.2722413 | I13: Average Historical P/E | J13: =M4 -> 0 | K13: ='SQURPHARMA Earnings Model T-1'!W42 -> 23.608125 | L13: =J13*K13 -> 0
A14: 45727 | B14: 217.7 | D14: =B14/$C$3 -> 9.2214113 | I14: Pharma Sector P/E
A15: 45726 | B15: 217.5 | D15: =B15/$C$3 -> 9.2129396 | I15: Average Price Per Share
A16: 45725 | B16: 217.5 | D16: =B16/$C$3 -> 9.2129396
A17: 45722 | B17: 217.5 | D17: =B17/$C$3 -> 9.2129396
A18: 45721 | B18: 217 | D18: =B18/$C$3 -> 9.1917605
A19: 45720 | B19: 216.9 | D19: =B19/$C$3 -> 9.1875246
A20: 45719 | B20: 217.1 | D20: =B20/$C$3 -> 9.1959963
A21: 45718 | B21: 216.3 | D21: =B21/$C$3 -> 9.1621096
A22: 45715 | B22: 216.5 | D22: =B22/$C$3 -> 9.1705813
A23: 45714 | B23: 216.2 | D23: =B23/$C$3 -> 9.1578738
A24: 45713 | B24: 216 | D24: =B24/$C$3 -> 9.1494021
A25: 45712 | B25: 215.8 | D25: =B25/$C$3 -> 9.1409304
A26: 45711 | B26: 216.1 | D26: =B26/$C$3 -> 9.1536379
A27: 45708 | B27: 215.9 | D27: =B27/$C$3 -> 9.1451663
... A181: 45475 | B181: 208.7 | D181: =B181/$C$3 -> 8.8401862
A182: 45473 | B182: 210.9 | C182: 21.4113 | D182: =B182/$C$182 -> 9.8499391
A183: 45470 | B183: 212.6 | D183: =B183/$C$182 -> 9.9293364
A184: 45469 | B184: 209.4 | D184: =B184/$C$182 -> 9.7798826
A185: 45468 | B185: 208.6 | D185: =B185/$C$182 -> 9.7425191
A186: 45467 | B186: 205.7 | D186: =B186/$C$182 -> 9.6070766
A187: 45466 | B187: 206.3 | D187: =B187/$C$182 -> 9.6350992
A188: 45463 | B188: 206.5 | D188: =B188/$C$182 -> 9.6444401
A189: 45462 | B189: 204.7 | D189: =B189/$C$182 -> 9.5603723
A190: 45456 | B190: 200 | D190: =B190/$C$182 -> 9.3408621
A191: 45455 | B191: 198.9 | D191: =B191/$C$182 -> 9.2894873
A192: 45454 | B192: 197.7 | D192: =B192/$C$182 -> 9.2334422
A193: 45453 | B193: 199.2 | D193: =B193/$C$182 -> 9.3034986
A194: 45452 | B194: 201.1 | D194: =B194/$C$182 -> 9.3922368
... A237: 45383 | B237: 218 | D237: =B237/$C$182 -> 10.18154

Sheet Sensitivity Analysis
C2: Historical | G2: Forecasted Data | M2: Growth Rate Calculation
B3: Year | C3: 2021 | D3: =C3+1 -> 2022 | E3: =D3+1 -> 2023 | F3: =E3+1 -> 2024 | G3: =F3+1 -> 2025 | H3: =G3+1 -> 2026 | I3: =H3+1 -> 2027 | J3: =I3+1 -> 2028 | M3: Year | N3: 2021 | O3: 2022 | P3: 2023 | Q3: 2024 | R3: 2025
B4: FCFF | C4: ='SQURPHARMA Earnings Model T-1'!H220 -> 7222.7591 | D4: ='SQURPHARMA Earnings Model T-1'!M220 -> 6691.5003 | E4: ='SQURPHARMA Earnings Model T-1'!R220 -> 5721.3663 | F4: ='SQURPHARMA Earnings Model T-1'!W220 -> 14347.562 | G4: ='SQURPHARMA Earnings Model T-1'!AB220 -> 17111.439 | H4: ='SQURPHARMA Earnings Model T-1'!AG220 -> 25465.006 | I4: ='SQURPHARMA Earnings Model T-1'!AL220 -> 25358.479 | J4: ='SQURPHARMA Earnings Model T-1'!AQ220 -> 10862.917 | M4: GDP Growth Rate | N4: =Workings!R3 -> 0.069386791 | O4: =Workings!S3 -> 0.070998288 | P4: =Workings!T3 -> 0.057751124 | Q4: =Workings!U3 -> 0.042232591 | R4: =Workings!V3 -> 0.049
B6: WACC | C6: ='SQURPHARMA Earnings Model T-1'!C275 -> 0.13126086 | M6: Terminal Growth Rate (5-year average) | R6: =AVERAGE(N4:R4) -> 0.057873759
B7: Growth Rate | C7: =R6 -> 0.057873759
B10: Terminal Value Calculation (Perpetuity Method) | M10: Sensitivity Analysis- Terminal Value
B11: PV of Forcasted FCFF | G11: {=NPV('SQURPHARMA Earnings Model T-1'!C275,'SQURPHARMA Earnings Model T-1'!AB220,'SQURPHARMA Earnings Model T-1'!AG220,'SQURPHARMA Earnings Model T-1'!AL220,'SQURPHARMA Earnings Model T-1'!AQ220)} -> 59173.171 | M11: Terminal Growth Rate | O11: Discount Rates
B12: Terminal Value | D12: 2025 | E12: =D12+1 -> 2026 | F12: =E12+1 -> 2027 | G12: =F12+1 -> 2028 | O12: =P12*(1-0.025) -> 0.12477985 | P12: =Q12*(1-0.025) -> 0.12797934 | Q12: =C6 -> 0.13126086 | R12: =Q12*(1+0.025) -> 0.13454238 | S12: =R12*(1+0.025) -> 0.13790594
D13: 0 | E13: 0 | F13: 0 | G13: =('SQURPHARMA Earnings Model T-1'!AQ220*(1+C7))/(C6-C7) -> 156588.77 | N13: =N14-0.01 -> 0.037873759 | O13: ='SQURPHARMA Earnings Model T-1'!$AQ$220*(1+$N$13)/(O12-$N$13) -> 129730.11 | P13: ='SQURPHARMA Earnings Model T-1'!$AQ$220*(1+$N$13)/(P12-$N$13) -> 125123.63 | Q13: ='SQURPHARMA Earnings Model T-1'!$AQ$220*(1+$N$13)/(Q12-$N$13) -> 120726.92 | R13: ='SQURPHARMA Earnings Model T-1'!$AQ$220*(1+$N$13)/(R12-$N$13) -> 116628.72 | S13: ='SQURPHARMA Earnings Model T-1'!$AQ$220*(1+$N$13)/(S12-$N$13) -> 112707.1
B14: PV of Terminal Value | G14: {=NPV(C6,D13:G13)} -> 95611.376 | N14: =N15-0.01 -> 0.047873759 | O14: ='SQURPHARMA Earnings Model T-1'!$AQ$220*(1+$N$14)/(O12-$N$14) -> 148011.24 | P14: ='SQURPHARMA Earnings Model T-1'!$AQ$220*(1+$N$14)/(P12-$N$14) -> 142099.55 | Q14: ='SQURPHARMA Earnings Model T-1'!$AQ$220*(1+$N$14)/(Q12-$N$14) -> 136507.52 | R14: ='SQURPHARMA Earnings Model T-1'!$AQ$220*(1+$N$14)/(R12-$N$14) -> 131338.96 | S14: ='SQURPHARMA Earnings Model T-1'!$AQ$220*(1+$N$14)/(S12-$N$14) -> 126432.2
N15: =C7 -> 0.057873759 | O15: ='SQURPHARMA Earnings Model T-1'!$AQ$220*(1+$N$15)/(O12-$N$15) -> 171757.08 | P15: ='SQURPHARMA Earnings Model T-1'!$AQ$220*(1+$N$15)/(P12-$N$15) -> 163918.42 | Q15: ='SQURPHARMA Earnings Model T-1'!$AQ$220*(1+$N$15)/(Q12-$N$15) -> 156588.77 | R15: ='SQURPHARMA Earnings Model T-1'!$AQ$220*(1+$N$15)/(R12-$N$15) -> 149886.56 | S15: ='SQURPHARMA Earnings Model T-1'!$AQ$220*(1+$N$15)/(S12-$N$15) -> 143587.18
N16: =N15+0.01 -> 0.067873759 | O16: ='SQURPHARMA Earnings Model T-1'!$AQ$220*(1+$N$16)/(O12-$N$16) -> 203848.55 | P16: ='SQURPHARMA Earnings Model T-1'!$AQ$220*(1+$N$16)/(P12-$N$16) -> 192997.47 | Q16: ='SQURPHARMA Earnings Model T-1'!$AQ$220*(1+$N$16)/(Q12-$N$16) -> 183006.08 | R16: ='SQURPHARMA Earnings Model T-1'!$AQ$220*(1+$N$16)/(R12-$N$16) -> 173998.27 | S16: ='SQURPHARMA Earnings Model T-1'!$AQ$220*(1+$N$16)/(S12-$N$16) -> 165641.35
B17: Enterprise Value Calculations | N17: =N16+0.01 -> 0.077873759 | O17: ='SQURPHARMA Earnings Model T-1'!$AQ$220*(1+$N$17)/(O12-$N$17) -> 249623.3 | P17: ='SQURPHARMA Earnings Model T-1'!$AQ$220*(1+$N$17)/(P12-$N$17) -> 233683.64 | Q17: ='SQURPHARMA Earnings Model T-1'!$AQ$220*(1+$N$17)/(Q12-$N$17) -> 219319.91 | R17: ='SQURPHARMA Earnings Model T-1'!$AQ$220*(1+$N$17)/(R12-$N$17) -> 206619.71 | S17: ='SQURPHARMA Earnings Model T-1'!$AQ$220*(1+$N$17)/(S12-$N$17) -> 195042.96
B18: PV of Forcasted FCFF | C18: =G11 -> 59173.171
B19: PV of Terminal Value | C19: =G14 -> 95611.376
B20: Total Enterprise Value | C20: =SUM(C18:C19) -> 154784.55 | M20: Sensitivity Analysis-PV of Terminal Value
B21: Cash and Cash Equivalent | C21: ='SQURPHARMA Earnings Model T-1'!AQ219 -> 93785.347 | M21: Terminal Growth Rate | O21: Discount Rates
B22: Interest Debt | O22: =O12 -> 0.12477985 | P22: =P12 -> 0.12797934 | Q22: =Q12 -> 0.13126086 | R22: =R12 -> 0.13454238 | S22: =S12 -> 0.13790594
B23: Equity Value | C23: =C20+C21 -> 248569.89 | N23: =N13 -> 0.037873759 | O23: =NPV($C$6,$D$13,$E$13,$F$13,O13) -> 79211.774 | P23: =NPV($C$6,$D$13,$E$13,$F$13,P13) -> 76399.11 | Q23: =NPV($C$6,$D$13,$E$13,$F$13,Q13) -> 73714.528 | R23: =NPV($C$6,$D$13,$E$13,$F$13,R13) -> 71212.208 | S23: =NPV($C$6,$D$13,$E$13,$F$13,S13) -> 68817.714
B24: Number of Shares Outstanding | D24: ='SQURPHARMA Earnings Model T-1'!AQ40 -> 886.45101 | N24: =N14 -> 0.047873759 | O24: =NPV($C$6,$D$13,$E$13,$F$13,O14) -> 90374.031 | P24: =NPV($C$6,$D$13,$E$13,$F$13,P14) -> 86764.417 | Q24: =NPV($C$6,$D$13,$E$13,$F$13,Q14) -> 83349.988 | R24: =NPV($C$6,$D$13,$E$13,$F$13,R14) -> 80194.119 | S24: =NPV($C$6,$D$13,$E$13,$F$13,S14) -> 77198.105
B25: Value Per Share | C25: =C23/D24 -> 280.41019 | N25: =N15 -> 0.057873759 | O25: =NPV($C$6,$D$13,$E$13,$F$13,O15) -> 104872.98 | P25: =NPV($C$6,$D$13,$E$13,$F$13,P15) -> 100086.78 | Q25: =NPV($C$6,$D$13,$E$13,$F$13,Q15) -> 95611.376 | R25: =NPV($C$6,$D$13,$E$13,$F$13,R15) -> 91519.079 | S25: =NPV($C$6,$D$13,$E$13,$F$13,S15) -> 87672.752
N26: =N16 -> 0.067873759 | O26: =NPV($C$6,$D$13,$E$13,$F$13,O16) -> 124467.68 | P26: =NPV($C$6,$D$13,$E$13,$F$13,P16) -> 117842.13 | Q26: =NPV($C$6,$D$13,$E$13,$F$13,Q16) -> 111741.5 | R26: =NPV($C$6,$D$13,$E$13,$F$13,R16) -> 106241.43 | S26: =NPV($C$6,$D$13,$E$13,$F$13,S16) -> 101138.78
N27: =N17 -> 0.077873759 | O27: =NPV($C$6,$D$13,$E$13,$F$13,O17) -> 152417.23 | P27: =NPV($C$6,$D$13,$E$13,$F$13,P17) -> 142684.66 | Q27: =NPV($C$6,$D$13,$E$13,$F$13,Q17) -> 133914.32 | R27: =NPV($C$6,$D$13,$E$13,$F$13,R17) -> 126159.72 | S27: =NPV($C$6,$D$13,$E$13,$F$13,S17) -> 119091.08
M30: Sensitivity Analysis- Enterprise Value
M31: Terminal Growth Rate | O31: Discount Rates
O32: =O12 -> 0.12477985 | P32: =P12 -> 0.12797934 | Q32: =Q12 -> 0.13126086 | R32: =R12 -> 0.13454238 | S32: =S12 -> 0.13790594
N33: =N13 -> 0.037873759 | O33: =SUM(O23,$C$18) -> 138384.94 | P33: =SUM(P23,$C$18) -> 135572.28 | Q33: =SUM(Q23,$C$18) -> 132887.7 | R33: =SUM(R23,$C$18) -> 130385.38 | S33: =SUM(S23,$C$18) -> 127990.88
N34: =N14 -> 0.047873759 | O34: =SUM(O24,$C$18) -> 149547.2 | P34: =SUM(P24,$C$18) -> 145937.59 | Q34: =SUM(Q24,$C$18) -> 142523.16 | R34: =SUM(R24,$C$18) -> 139367.29 | S34: =SUM(S24,$C$18) -> 136371.28
N35: =N15 -> 0.057873759 | O35: =SUM(O25,$C$18) -> 164046.15 | P35: =SUM(P25,$C$18) -> 159259.95 | Q35: =SUM(Q25,$C$18) -> 154784.55 | R35: =SUM(R25,$C$18) -> 150692.25 | S35: =SUM(S25,$C$18) -> 146845.92
N36: =N16 -> 0.067873759 | O36: =SUM(O26,$C$18) -> 183640.85 | P36: =SUM(P26,$C$18) -> 177015.3 | Q36: =SUM(Q26,$C$18) -> 170914.67 | R36: =SUM(R26,$C$18) -> 165414.6 | S36: =SUM(S26,$C$18) -> 160311.95
N37: =N17 -> 0.077873759 | O37: =SUM(O27,$C$18) -> 211590.4 | P37: =SUM(P27,$C$18) -> 201857.83 | Q37: =SUM(Q27,$C$18) -> 193087.49 | R37: =SUM(R27,$C$18) -> 185332.89 | S37: =SUM(S27,$C$18) -> 178264.25
M40: Sensitivity Analysis- Value per Share
M41: Terminal Growth Rate | O41: Discount Rates
O42: =O12 -> 0.12477985 | P42: =P12 -> 0.12797934 | Q42: =Q12 -> 0.13126086 | R42: =R12 -> 0.13454238 | S42: =S12 -> 0.13790594
N43: =N13 -> 0.037873759 | O43: =($C$21+$C$22+O33)/$D$24 -> 261.9099 | P43: =($C$21+$C$22+P33)/$D$24 -> 258.73695 | Q43: =($C$21+$C$22+Q33)/$D$24 -> 255.70849 | R43: =($C$21+$C$22+R33)/$D$24 -> 252.88563 | S43: =($C$21+$C$22+S33)/$D$24 -> 250.18442
N44: =N14 -> 0.047873759 | O44: =($C$21+$C$22+O34)/$D$24 -> 274.50197 | P44: =($C$21+$C$22+P34)/$D$24 -> 270.42999 | Q44: =($C$21+$C$22+Q34)/$D$24 -> 266.57819 | R44: =($C$21+$C$22+R34)/$D$24 -> 263.01807 | S44: =($C$21+$C$22+S34)/$D$24 -> 259.63829
N45: =N15 -> 0.057873759 | O45: =($C$21+$C$22+O35)/$D$24 -> 290.85815 | P45: =($C$21+$C$22+P35)/$D$24 -> 285.45886 | Q45: =($C$21+$C$22+Q35)/$D$24 -> 280.41019 | R45: =($C$21+$C$22+R35)/$D$24 -> 275.79369 | S45: =($C$21+$C$22+S35)/$D$24 -> 271.45467
N46: =N16 -> 0.067873759 | O46: =($C$21+$C$22+O36)/$D$24 -> 312.9628 | P46: =($C$21+$C$22+P36)/$D$24 -> 305.48857 | Q46: =($C$21+$C$22+Q36)/$D$24 -> 298.60648 | R46: =($C$21+$C$22+R36)/$D$24 -> 292.40188 | S46: =($C$21+$C$22+S36)/$D$24 -> 286.64562
N47: =N17 -> 0.077873759 | O47: =($C$21+$C$22+O37)/$D$24 -> 344.49253 | P47: =($C$21+$C$22+P37)/$D$24 -> 333.51327 | Q47: =($C$21+$C$22+Q37)/$D$24 -> 323.61951 | R47: =($C$21+$C$22+R37)/$D$24 -> 314.87158 | S47: =($C$21+$C$22+S37)/$D$24 -> 306.8975

Sheet Peer Comparison
A3: Peer Comparison
A4: Company Name | B4: Particulars | C4: P/E | D4: P/NAV | E4: P/BV | F4: Price
A5: SQURPHARMA | B5: SQURPHARMA | C5: =E16/C16 -> 8.8987717 | D5: =E16/D16 -> 1.4790567 | E5: 1.4 | F5: =E16 -> 210.1
A6: Beximco Pharmaceuticals PLC | B6: BXPHARMA | C6: =E17/C17 -> 6.6947207 | D6: =E17/D17 -> 0.81410495 | E6: 1 | F6: =E17 -> 87.5
A7: Advanced Chemical Industries PLC | B7: ACI | C7: - | D7: =E18/D18 -> 2.0478227 | E7: 1.7 | F7: =E18 -> 186.7
A8: Reckitt Benckiser (Bangladesh) PLC | B8: RECKITTBEN | C8: =E19/C19 -> 20.73255 | D8: =E19/D19 -> 9.4113621 | E8: 25.6 | F8: =E19 -> 3300
A9: The ACME Laboratories Limited | B9: ACMELAB | C9: =E20/C20 -> 6.2618432 | D9: =E20/D20 -> 0.61407213 | E9: 0.6 | F9: =E20 -> 72.7
A10: Renata PLC | B10: RENATA | C10: =E21/C21 -> 15.528069 | D10: =E21/D21 -> 1.6565164 | E10: 1.3 | F10: =E21 -> 489.6
A11: Sector Avg. PE | C11: =AVERAGE(C5:C10) -> 11.623191 | D11: =AVERAGE(D5:D10) -> 2.6704892 | E11: =AVERAGE(E5:E10) -> 5.2666667
A14: Peer Comparison
A15: Company Name | B15: Particulars | C15: EPS | D15: NAV | E15: Price
A16: SQURPHARMA | B16: SQURPHARMA | C16: 23.61 | D16: 142.05 | E16: 210.1
A17: Beximco Pharmaceuticals PLC | B17: BXPHARMA | C17: 13.07 | D17: 107.48 | E17: 87.5
A18: Advanced Chemical Industries PLC | B18: ACI | C18: -18.25 | D18: 91.17 | E18: 186.7
A19: Reckitt Benckiser (Bangladesh) PLC | B19: RECKITTBEN | C19: 159.17 | D19: 350.64 | E19: 3300
A20: The ACME Laboratories Limited | B20: ACMELAB | C20: 11.61 | D20: 118.39 | E20: 72.7
A21: Renata PLC | B21: RENATA | C21: 31.53 | D21: 295.56 | E21: 489.6

Sheet Altman Z Score
B2: Z-score = 1.2 (Net working capital/Total assets) + 1.4 (Retained earnings/Total assets) + 3.3 (EBIT/Total assets) + 0.6 (Market value of equity/Book value of liabilities) + 1.0 (Sales/Total assets)
C5: Net Working Capital to Total Assets | D5: =('SQURPHARMA Earnings Model T-1'!W89-'SQURPHARMA Earnings Model T-1'!W112-'SQURPHARMA Earnings Model T-1'!W108)/'SQURPHARMA Earnings Model T-1'!W96 -> 0.48621312
C6: Retained Earnings to Total Assets | D6: ='SQURPHARMA Earnings Model T-1'!W124/'SQURPHARMA Earnings Model T-1'!W96 -> 0.86053592
C7: EBIT to Total Assets | D7: ='SQURPHARMA Earnings Model T-1'!W25/'SQURPHARMA Earnings Model T-1'!W96 -> 0.14499162
C8: Market Value of Equity to Total Liabilities | D8: ='SQURPHARMA Earnings Model T-1'!W117/('SQURPHARMA Earnings Model T-1'!W112+'SQURPHARMA Earnings Model T-1'!W108) -> 1.3199925
C9: Sales to Total Assets | D9: ='SQURPHARMA Earnings Model T-1'!W17/'SQURPHARMA Earnings Model T-1'!W96 -> 0.52851713
C11: Z Score | D11: =1.2*D5+1.4*D6+3.3*D7+0.6*D8+1*D9 -> 3.587191 | F11: Scores greater than 3.00 indicates a low probability of bankruptcy
C13: SQUARE Pharma has a low probability of bankruptcy

Sheet Beneish Model
B3: Derived Variables | D3: Value of variables
B4: Days Sales in Receivables Index (DSRI) | D4: =(D27/D25)/(C27/C25) -> 0.65841284
B5: Gross Margin Index (GMI) | D5: =((C25-C26)/C25)/((D25-D26)/D25) -> 1.0463577
B6: Asset Quality Index (AQI) | D6: =(1-(D29+D28)/D31)/(1-(C29+C28)/C31) -> 1.2241116
B7: Sales Growth Index (SGI) | D7: =D25/C25 -> 1.1171892
B8: Depreciation Index (DEPI) | D8: =C37/D37 -> 1.0559213
B9: Sales, General, and Administrative Expenses Index (SGAI) | D9: =(D32/D25)/(C32/C25) -> 0.9423259
B10: Leverage Index (LVGI) | D10: =((D36+D35)/D31)/((C36+C35)/C31) -> 1.0002875
B11: Total Accruals to Total Assets (TATA) | D11: =(D33-D34)/D25 -> 0.03421621
C14: M-Score | D14: Probability
B15: 5 variable equation | C15: =-6.065+0.823*D4+0.906*D5+0.593*D6+0.717*D7+0.107*D8 -> -2.9352197 | D15: =1-0.9984 -> 0.0016
B16: 8 variable equation | C16: =-4.84 +0.92*D4+0.528*D5+0.404*D6+0.892*D7+0.115*D8-0.172*D9+ 4.679*D11-0.327*D10 -> -2.3983549 | D16: =1-0.9918 -> 0.0082
B19: Notes
B20: 5 variable equation | C20: M= -6.065 +.823 DSRI +.906 GMI +.593 AQI +.717 SGI +.107 DEPI
B21: 8 variable equation | C21: M= -4.84 + .920 DSRI +.528 GMI + .404 AQI+ .892 SGI + .115 DEPI - .172 SGAI + 4.679 Accrual - .327 Leverage
B23: Parameters
B24: Year | C24: 2023 | D24: 2024
B25: Net Sales | C25: ='SQURPHARMA Earnings Model T-1'!R17 -> 62747.683 | D25: ='SQURPHARMA Earnings Model T-1'!W17 -> 70101.031
B26: Cost of goods | C26: ='SQURPHARMA Earnings Model T-1'!R18 -> 31772.093 | D26: ='SQURPHARMA Earnings Model T-1'!W18 -> 37028.602
B27: Net Receivables | C27: ='SQURPHARMA Earnings Model T-1'!R83 -> 6122.2941 | D27: ='SQURPHARMA Earnings Model T-1'!W83 -> 4503.3862
B28: Current assets (CA) | C28: ='SQURPHARMA Earnings Model T-1'!R89 -> 70486.795 | D28: ='SQURPHARMA Earnings Model T-1'!W89 -> 71205.521
B29: Property, Plant and Equipment (PPE) | C29: ='SQURPHARMA Earnings Model T-1'!R91 -> 26058.822 | D29: ='SQURPHARMA Earnings Model T-1'!W91 -> 27750.006
B30: Depreciation | C30: ='SQURPHARMA Earnings Model T-1'!R162 -> 2309.8994 | D30: ='SQURPHARMA Earnings Model T-1'!W162 -> 2318.6534
B31: Total Assets (TA) | C31: ='SQURPHARMA Earnings Model T-1'!R96 -> 121815.98 | D31: ='SQURPHARMA Earnings Model T-1'!W96 -> 132637.2
B32: SGA Expense | C32: ='SQURPHARMA Earnings Model T-1'!R23 -> 13469.246 | D32: ='SQURPHARMA Earnings Model T-1'!W23 -> 14179.833
B33: Net Income | C33: ='SQURPHARMA Earnings Model T-1'!R39 -> 18980.024 | D33: ='SQURPHARMA Earnings Model T-1'!W39 -> 20927.446
B34: Cash Flow From Operations | C34: ='SQURPHARMA Earnings Model T-1'!R189 -> 8545.6143 | D34: ='SQURPHARMA Earnings Model T-1'!W189 -> 18528.854
B35: Current Liabilites | C35: ='SQURPHARMA Earnings Model T-1'!R108 -> 4229.1457 | D35: ='SQURPHARMA Earnings Model T-1'!W108 -> 5281.9549
B36: Long-term Debt | C36: ='SQURPHARMA Earnings Model T-1'!R110 -> 1368.3569 | D36: ='SQURPHARMA Earnings Model T-1'!W110 -> 814.53983
B37: Depreciation Rate | C37: =C30/(C30+C29) -> 0.081424165 | D37: =D30/(D30+D29) -> 0.077111964

Sheet Workings
Q1: GDP & CAGR
R2: 2021 | S2: 2022 | T2: 2023 | U2: 2024 | V2: 2025 | W2: 2026E | X2: 2027E | Y2: 2028E | BE2: Translation reserve
B3: SALES GROWTH RATE | Q3: GDP | R3: 0.069386791 | S3: 0.070998288 | T3: 0.057751124 | U3: 0.042232591 | V3: 0.049 | W3: 0.049 | X3: 0.063 | Y3: 0.07
C4: Q1 | D4: Q2 | E4: Q3 | F4: Q4 | Q4: Average GDP Growth | V4: =AVERAGE(R3:V3) -> 0.057873759 | Y4: =AVERAGE(W3:Y3) -> 0.060666667 | AB4: Profit for the Year Attributable to Non-Controlling Interest | BE4: 2024-2025 | BF4: Q1 | BG4: Q2 | BH4: Q3
B5: 2020 | C5: ='SQURPHARMA Earnings Model T-1'!D50 -> 0 | D5: ='SQURPHARMA Earnings Model T-1'!E50 -> -0.016660965 | E5: ='SQURPHARMA Earnings Model T-1'!F50 -> 0.032675988 | F5: ='SQURPHARMA Earnings Model T-1'!G50 -> 0.017315659 | L5: DSO | M5: Ending receivables/ Net revenue * 365 | Q5: Average industry CAGR | V5: 0.0897 | Y5: 0.15 | AC5: Jun-24 | AD5: Sept-24 | AE5: Dec-24 | AF5: Mar-25 | AG5: Jun-25 | AH5: Jun-25 | AI5: Sept-25 | AJ5: Dec-25 | AK5: Mar-26 | AL5: Jun-26 | AM5: Jun-26 | AN5: Sept-26 | AO5: Dec-26 | AP5: Mar-27 | AQ5: Jun-27 | AR5: Jun-27 | AS5: Sept-27 | AT5: Dec-27 | AU5: Mar-28 | AV5: Jun-28 | AW5: Jun-28 | BE5: Translation Reserve | BF5: ='SQURPHARMA Earnings Model T-1'!X122 -> 124.72198 | BG5: ='SQURPHARMA Earnings Model T-1'!Y122 -> 124.60672 | BH5: ='SQURPHARMA Earnings Model T-1'!Z122 -> 131.49156
B6: 2021 | C6: ='SQURPHARMA Earnings Model T-1'!I50 -> 0.14514418 | D6: ='SQURPHARMA Earnings Model T-1'!J50 -> -0.045808348 | E6: ='SQURPHARMA Earnings Model T-1'!K50 -> 0.032026261 | F6: ='SQURPHARMA Earnings Model T-1'!L50 -> -0.052853204 | Q6: Average CAGR of Square Pharma | V6: 0.1039 | Y6: =Y7+(V6-V5) -> 0.13669291 | AC6: 4Q24 | AD6: 1Q25 | AE6: 2Q25 | AF6: 3Q25 | AG6: 4Q25 E | AH6: 2025E | AI6: 1Q26E | AJ6: 2Q26E | AK6: 3Q26E | AL6: 4Q26E | AM6: 2026E | AN6: 1Q27E | AO6: 2Q27E | AP6: 3Q27E | AQ6: 4Q27E | AR6: 2027E | AS6: 1Q28E | AT6: 2Q28E | AU6: 3Q28E | AV6: 4Q28E | AW6: 2028E | BE6: Growth | BG6: =BG5/BF5-1 -> -0.00092410335 | BH6: =BH5/BG5-1 -> 0.055252532
B7: 2022 | C7: ='SQURPHARMA Earnings Model T-1'!N50 -> 0.15811281 | D7: ='SQURPHARMA Earnings Model T-1'!O50 -> 0.0073088565 | E7: ='SQURPHARMA Earnings Model T-1'!P50 -> -0.018515777 | F7: ='SQURPHARMA Earnings Model T-1'!Q50 -> -0.080803183 | L7: Accounts Receivable (A/R) | Q7: Adjusted Average industry CAGR | Y7: =Y4+(V5-V4)+3% -> 0.12249291 | AC7: =1.609102-0.866054 -> 0.743048 | AD7: 0.732701 | AE7: =1.557567-AD7 -> 0.824866 | AF7: =2.470216-SUM(AD7:AE7) -> 0.912649 | AG7: =AF7*(1+AC9) -> 0.97905451 | AI7: =AG7*(1+$AC$9) -> 1.0502918 | AJ7: =AI7*(1+$AC$9) -> 1.1267124 | AK7: =AJ7*(1+$AC$9) -> 1.2086934 | AL7: =AK7*(1+$AC$9) -> 1.2966395 | AN7: =AL7*(1+$AC$9) -> 1.3909846 | AO7: =AN7*(1+$AC$9) -> 1.4921945 | AP7: =AO7*(1+$AC$9) -> 1.6007685 | AQ7: =AP7*(1+$AC$9) -> 1.7172424 | AS7: =AQ7*(1+$AC$9) -> 1.8421912 | AT7: =AS7*(1+$AC$9) -> 1.9762314 | AU7: =AT7*(1+$AC$9) -> 2.1200245 | AV7: =AU7*(1+$AC$9) -> 2.2742802 | BE7: Average Growth | BF7: =AVERAGE(BF6:BH6) -> 0.027164214
B8: 2023 | C8: {='SQURPHARMA Earnings Model T-1'!S50:V50} -> 0.2640159 | D8: 0.0032369503 | E8: -0.069653059 | F8: -0.077498 | L8: DSO × Net Revenue ÷ 365. | AB8: Growth | AD8: =AD7/AC7-1 -> -0.013925076 | AE8: =AE7/AD7-1 -> 0.12578801 | AF8: =AF7/AE7-1 -> 0.10642092
B9: 2024 | C9: ='SQURPHARMA Earnings Model T-1'!X50 -> 0.11658958 | D9: ='SQURPHARMA Earnings Model T-1'!Y50 -> 0.12531795 | E9: ='SQURPHARMA Earnings Model T-1'!Z50 -> 0.0079026697 | L9: DSO × Net Revenue ÷ Days in Quarter (≈ 90) | AB9: average | AC9: =AVERAGE(AD8:AF8) -> 0.072761285
B10: Average | C10: =AVERAGE(C6:C9) -> 0.17096562 | D10: =AVERAGE(D5:D9) -> 0.014678889 | E10: =AVERAGE(E5:E9) -> -0.0031127834 | F10: =AVERAGE(F6:F8) -> -0.070384796
B12: Seasonality Index of Sales | L12: Inventory | P12: DIO | Q12: inventory / Cost of good sold * 365
C13: Q1 | D13: Q2 | E13: Q3 | F13: Q4 | L13: DIO × COGS ÷ 365.
B14: 2020 | C14: ='SQURPHARMA Earnings Model T-1'!D17/'SQURPHARMA Earnings Model T-1'!$H$17 -> 0.24802425 | D14: ='SQURPHARMA Earnings Model T-1'!E17/'SQURPHARMA Earnings Model T-1'!$H$17 -> 0.24389193 | E14: ='SQURPHARMA Earnings Model T-1'!F17/'SQURPHARMA Earnings Model T-1'!$H$17 -> 0.25186134 | F14: ='SQURPHARMA Earnings Model T-1'!G17/'SQURPHARMA Earnings Model T-1'!$H$17 -> 0.25622248 | L14: DIO × COGS ÷ Days in Quarter.
B15: 2021 | C15: ='SQURPHARMA Earnings Model T-1'!I17/'SQURPHARMA Earnings Model T-1'!$M$17 -> 0.25828807 | D15: ='SQURPHARMA Earnings Model T-1'!J17/'SQURPHARMA Earnings Model T-1'!$M$17 -> 0.24645632 | E15: ='SQURPHARMA Earnings Model T-1'!K17/'SQURPHARMA Earnings Model T-1'!$M$17 -> 0.25434939 | F15: ='SQURPHARMA Earnings Model T-1'!L17/'SQURPHARMA Earnings Model T-1'!$M$17 -> 0.24090621
B16: 2022 | C16: ='SQURPHARMA Earnings Model T-1'!N17/'SQURPHARMA Earnings Model T-1'!$R$17 -> 0.25609915 | D16: ='SQURPHARMA Earnings Model T-1'!O17/'SQURPHARMA Earnings Model T-1'!$R$17 -> 0.25797094 | E16: ='SQURPHARMA Earnings Model T-1'!P17/'SQURPHARMA Earnings Model T-1'!$R$17 -> 0.25319441 | F16: ='SQURPHARMA Earnings Model T-1'!Q17/'SQURPHARMA Earnings Model T-1'!$R$17 -> 0.2327355 | L16: Cash | M16: CF er last amount
B17: 2023 | C17: ='SQURPHARMA Earnings Model T-1'!S17/'SQURPHARMA Earnings Model T-1'!$W$17 -> 0.26332279 | D17: ='SQURPHARMA Earnings Model T-1'!T17/'SQURPHARMA Earnings Model T-1'!$W$17 -> 0.26417515 | E17: ='SQURPHARMA Earnings Model T-1'!U17/'SQURPHARMA Earnings Model T-1'!$W$17 -> 0.24577455 | F17: ='SQURPHARMA Earnings Model T-1'!V17/'SQURPHARMA Earnings Model T-1'!$W$17 -> 0.22672751 | N17: Avg rec
B18: 2024 | C18: ='SQURPHARMA Earnings Model T-1'!X17/'SQURPHARMA Earnings Model T-1'!$AB$17 -> 0.23180834 | D18: ='SQURPHARMA Earnings Model T-1'!Y17/'SQURPHARMA Earnings Model T-1'!$AB$17 -> 0.26085808 | E18: ='SQURPHARMA Earnings Model T-1'!Z17/'SQURPHARMA Earnings Model T-1'!$AB$17 -> 0.26291956 | M18: Q1 | N18: Q2 | O18: Q3 | P18: Q4 | Q18: Year
B19: Average | C19: =AVERAGE(C15:C18) -> 0.25237959 | D19: =AVERAGE(D14:D18) -> 0.25467049 | E19: =AVERAGE(E14:E18) -> 0.25361985 | F19: =AVERAGE(F14:F17) -> 0.23914793 | L19: 2025
L20: 2026
B21: Gross margin | L21: Recceivables Turnover
C22: Q1 | D22: Q2 | E22: Q3 | F22: Q4 | M22: Q1 | N22: Q2 | O22: Q3 | P22: Q4 | Q22: Year | AQ22: 2025 | AV22: 2026 | BA22: 2027
B23: 2020 | C23: 0.51 | D23: 0.53 | E23: 0.51 | F23: 0.49 | L23: 2025 | AP23: Est | AQ23: Est | AR23: Est | AS23: Est | AT23: Est | AU23: Est | AV23: Est | AW23: Est | AX23: Est | AY23: Est | AZ23: Est | BA23: Est | BB23: Est | BC23: Est | BD23: Est
B24: 2021 | C24: 0.51 | D24: 0.53 | E24: 0.51 | F24: 0.5 | L24: 2026
B25: 2022 | C25: 0.52 | D25: 0.53 | E25: 0.48 | F25: 0.44
B26: 2023 | C26: 0.53 | D26: 0.49 | E26: 0.51 | F26: 0.34
B27: 2024 | C27: 0.5 | D27: 0.45 | E27: 0.48 | Q27: Days sales outstanding | S27: 12.5 | T27: 12.272057 | U27: 12.719516 | V27: 16.757372 | W27: =SUM(S27:V27) -> 54.248945 | X27: 13.638551 | Y27: 13.876214 | Z27: 17.161917 | AA27: 20.099411 | AB27: =SUM(X27:AA27) -> 64.776092 | AC27: 20.269542 | AD27: 21.78168 | AE27: 22.049395 | AF27: 30.552273 | AG27: =SUM(AC27:AF27) -> 94.65289 | AH27: 26.927458 | AI27: 23.96471 | AJ27: 24.656224 | AK27: 25.494824 | AL27: =SUM(AH27:AK27) -> 101.04322 | AM27: 24.799501 | AN27: 22.361931 | AO27: 28.040082 | AP27: =AO27*(AK27/AJ27) -> 28.993773 | AQ27: =SUM(AM27:AP27) -> 104.19529 | AR27: =AP27*(AM27/AK27) -> 28.203023 | AS27: =AR27*(AN27/AM27) -> 25.430917 | AT27: =AS27*(AO27/AN27) -> 31.888346 | AU27: =AT27*(AP27/AO27) -> 32.972923 | AV27: =SUM(AR27:AU27) -> 118.49521
B28: Average | C28: =AVERAGE(C23:C27) -> 0.514 | D28: =AVERAGE(D23:D27) -> 0.506 | E28: =AVERAGE(E23:E27) -> 0.498 | F28: =AVERAGE(F23:F26) -> 0.4425
L29: DSO | AP29: =AQ27-SUM(AM27:AO27) -> 28.993773
B30: Operating margin | M30: Q1 | N30: Q2 | O30: Q3 | P30: Q4 | Q30: Year
C31: Q1 | D31: Q2 | E31: Q3 | F31: Q4 | L31: 2020 | AJ31: =AVERAGE(AG27,AL27) -> 97.848053
B32: 2020 | C32: 0.3384081 | D32: 0.34007585 | E32: 0.32294063 | F32: 0.28050951 | L32: 2021
B33: 2021 | C33: 0.34764982 | D33: 0.33768364 | E33: 0.32604125 | F33: 0.26481455 | L33: 2022
B34: 2022 | C34: 0.36020915 | D34: 0.32762878 | E34: 0.27849712 | F34: 0.18524891 | L34: 2023 | AH34: Avg | AI34: =AVERAGE(S27,X27,AC27,AH27,AM27) -> 19.62701 | AJ34: =AVERAGE(T27,Y27,AD27,AI27,AN27) -> 18.851318 | AK34: =AVERAGE(U27,Z27,AE27,AJ27,AO27) -> 20.925427 | AL34: =AVERAGE(V27,AA27,AF27,AK27,AP27) -> 24.379531 | AM34: =AVERAGE(W27,AB27,AG27,AL27,AQ27) -> 83.783286
B35: 2023 | C35: 0.34530094 | D35: 0.27116325 | E35: 0.25738261 | F35: 0.21399414 | L35: 2024 | AH35: 2 avg | AI35: =AVERAGE(AH27,AM27) -> 25.86348 | AJ35: =AVERAGE(AI27,AN27) -> 23.163321 | AK35: =AVERAGE(AJ27,AO27) -> 26.348153 | AL35: =AVERAGE(AK27,AP27) -> 27.244299 | AM35: =AVERAGE(AL27,AQ27) -> 102.61925
B36: 2024 | C36: 0.31351993 | D36: 0.27195457 | E36: 0.26411324 | L36: 2025 | P36: =('SQURPHARMA Earnings Model T-1'!Y83/'SQURPHARMA Earnings Model T-1'!AA17)*90 -> 22.352134 | AH36: 3 avg | AI36: =AVERAGE(AC27,AH27,AM27) -> 23.998834 | AJ36: =AVERAGE(AD27,AI27,AN27) -> 22.702774 | AK36: =AVERAGE(AE27,AJ27,AO27) -> 24.915233 | AL36: =AVERAGE(AF27,AK27,AP27) -> 28.346957 | AM36: =AVERAGE(AG27,AL27,AQ27) -> 99.963798
B37: Average | C37: =AVERAGE(C32:C36) -> 0.34101759 | D37: =AVERAGE(D32:D36) -> 0.30970122 | E37: =AVERAGE(E32:E36) -> 0.28979497 | F37: =AVERAGE(F32:F36) -> 0.23614178 | L37: 2026
B39: Selling and Distribution Expenses to Net Revenue | L39: Account Receivables | X39: Receivables turnover | AA39: 7.3337337 | AB39: 7.0757412 | AC39: 5.3707706 | AD39: 19.780246 | AE39: 6.5989417 | AF39: 6.485919 | AG39: 5.2441693 | AH39: 4.4777433 | AI39: 22.806773 | AJ39: 4.4401595 | AK39: 4.1319127 | AL39: 4.0817447 | AM39: 2.945771 | AN39: 15.599588 | AO39: 3.3423133 | AP39: 3.7555222 | AQ39: 3.650194 | AR39: 3.5301283 | AS39: 14.278158 | AT39: 3.6291052 | AU39: 4.0246971 | AV39: 3.2096911
C40: Q1 | D40: Q2 | E40: Q3 | F40: Q4 | M40: Q1 | N40: Q2 | O40: Q3 | P40: Q4 | Q40: Year
B41: 2020 | C41: 0.15 | D41: 0.17 | E41: 0.17 | F41: 0.18 | L41: 2025 | P41: =(P36/90)*'SQURPHARMA Earnings Model T-1'!AA17 -> 4647.2469
B42: 2021 | C42: 0.15 | D42: 0.18 | E42: 0.17 | F42: 0.24 | L42: 2026
B43: 2022 | C43: 0.16 | D43: 0.18 | E43: 0.19 | F43: 0.22
B44: 2023 | C44: 0.17 | D44: 0.19 | E44: 0.23 | F44: 0.09
B45: 2024 | C45: 0.17 | D45: 0.15 | E45: 0.19
B46: Averge | C46: =AVERAGE(C41:C45) -> 0.16 | D46: =AVERAGE(D41:D45) -> 0.174 | E46: =AVERAGE(E41:E45) -> 0.19 | F46: =AVERAGE(F41:F45) -> 0.1825
B48: Administrative Expense to Net Revenue
C49: Q1 | D49: Q2 | E49: Q3 | F49: Q4
B50: 2020 | C50: 0.02 | D50: 0.02 | E50: 0.02 | F50: 0.03
B51: 2021 | C51: 0.02 | D51: 0.02 | E51: 0.02 | F51: 0.03
B52: 2022 | C52: 0.02 | D52: 0.02 | E52: 0.02 | F52: 0.03
B53: 2023 | C53: 0.02 | D53: 0.02 | E53: 0.02 | F53: 0.04
B54: 2024 | C54: 0.02 | D54: 0.02 | E54: 0.03
B55: Average | C55: =AVERAGE(C50:C54) -> 0.02 | D55: =AVERAGE(D50:D54) -> 0.02 | E55: =AVERAGE(E50:E54) -> 0.022 | F55: =AVERAGE(F50:F54) -> 0.0325
B58: Proportion | C58: Selling and Distribution Expenses | G58: Administrative Expenses | K58: Finance Cost
B59: Year | C59: Q1 | D59: Q2 | E59: Q3 | F59: Q4 | G59: Q1 | H59: Q2 | I59: Q3 | J59: Q4 | K59: Q1 | L59: Q2 | M59: Q3 | N59: Q4
B60: 2020 | C60: ='SQURPHARMA Earnings Model T-1'!D20/'SQURPHARMA Earnings Model T-1'!D23 -> 0.88445609 | D60: ='SQURPHARMA Earnings Model T-1'!E20/'SQURPHARMA Earnings Model T-1'!E23 -> 0.87472769 | E60: ='SQURPHARMA Earnings Model T-1'!F20/'SQURPHARMA Earnings Model T-1'!F23 -> 0.87137923 | F60: ='SQURPHARMA Earnings Model T-1'!G20/'SQURPHARMA Earnings Model T-1'!G23 -> 0.87311076 | G60: ='SQURPHARMA Earnings Model T-1'!E21/'SQURPHARMA Earnings Model T-1'!E23 -> 0.12527231 | H60: ='SQURPHARMA Earnings Model T-1'!F21/'SQURPHARMA Earnings Model T-1'!F23 -> 0.12861919 | I60: ='SQURPHARMA Earnings Model T-1'!G21/'SQURPHARMA Earnings Model T-1'!G23 -> 0.12688768 | J60: ='SQURPHARMA Earnings Model T-1'!H21/'SQURPHARMA Earnings Model T-1'!H23 -> 0.1244126 | K60: ='SQURPHARMA Earnings Model T-1'!D22/'SQURPHARMA Earnings Model T-1'!D23 -> 2.4401492e-06 | L60: ='SQURPHARMA Earnings Model T-1'!E22/'SQURPHARMA Earnings Model T-1'!E23 -> 0 | M60: ='SQURPHARMA Earnings Model T-1'!F22/'SQURPHARMA Earnings Model T-1'!F23 -> 1.5785377e-06 | N60: ='SQURPHARMA Earnings Model T-1'!G22/'SQURPHARMA Earnings Model T-1'!G23 -> 1.5591597e-06 | P60: =C60+G60+K60 -> 1.0097308 | Q60: =D60+H60+L60 -> 1.0033469 | R60: =E60+I60+M60 -> 0.9982685 | S60: =F60+J60+N60 -> 0.99752492
B61: 2021 | C61: ='SQURPHARMA Earnings Model T-1'!I20/'SQURPHARMA Earnings Model T-1'!I23 -> 0.89385994 | D61: ='SQURPHARMA Earnings Model T-1'!J20/'SQURPHARMA Earnings Model T-1'!J23 -> 0.88047085 | E61: ='SQURPHARMA Earnings Model T-1'!K20/'SQURPHARMA Earnings Model T-1'!K23 -> 0.87469218 | F61: ='SQURPHARMA Earnings Model T-1'!L20/'SQURPHARMA Earnings Model T-1'!L23 -> 0.87936942 | G61: ='SQURPHARMA Earnings Model T-1'!I21/'SQURPHARMA Earnings Model T-1'!I23 -> 0.10613115 | H61: ='SQURPHARMA Earnings Model T-1'!J21/'SQURPHARMA Earnings Model T-1'!J23 -> 0.11952891 | I61: ='SQURPHARMA Earnings Model T-1'!K21/'SQURPHARMA Earnings Model T-1'!K23 -> 0.12530693 | J61: ='SQURPHARMA Earnings Model T-1'!L21/'SQURPHARMA Earnings Model T-1'!L23 -> 0.12062941 | K61: ='SQURPHARMA Earnings Model T-1'!I22/'SQURPHARMA Earnings Model T-1'!I23 -> 8.9124002e-06 | L61: ='SQURPHARMA Earnings Model T-1'!J22/'SQURPHARMA Earnings Model T-1'!J23 -> 2.4550742e-07 | M61: ='SQURPHARMA Earnings Model T-1'!K22/'SQURPHARMA Earnings Model T-1'!K23 -> 8.9172408e-07 | N61: ='SQURPHARMA Earnings Model T-1'!L22/'SQURPHARMA Earnings Model T-1'!L23 -> 1.1697475e-06 | P61: =C61+G61+K61 -> 1 | Q61: =D61+H61+L61 -> 1 | R61: =E61+I61+M61 -> 1 | S61: =F61+J61+N61 -> 1
B62: 2022 | C62: ='SQURPHARMA Earnings Model T-1'!N20/'SQURPHARMA Earnings Model T-1'!N23 -> 0.88336516 | D62: ='SQURPHARMA Earnings Model T-1'!O20/'SQURPHARMA Earnings Model T-1'!O23 -> 0.87669445 | E62: ='SQURPHARMA Earnings Model T-1'!P20/'SQURPHARMA Earnings Model T-1'!P23 -> 0.88491138 | F62: ='SQURPHARMA Earnings Model T-1'!Q20/'SQURPHARMA Earnings Model T-1'!Q23 -> 0.86532901 | G62: ='SQURPHARMA Earnings Model T-1'!N21/'SQURPHARMA Earnings Model T-1'!N23 -> 0.11663484 | H62: ='SQURPHARMA Earnings Model T-1'!O21/'SQURPHARMA Earnings Model T-1'!O23 -> 0.11328054 | I62: ='SQURPHARMA Earnings Model T-1'!P21/'SQURPHARMA Earnings Model T-1'!P23 -> 0.10283956 | J62: ='SQURPHARMA Earnings Model T-1'!Q21/'SQURPHARMA Earnings Model T-1'!Q23 -> 0.12305499 | K62: ='SQURPHARMA Earnings Model T-1'!N22/'SQURPHARMA Earnings Model T-1'!N23 -> 0 | L62: ='SQURPHARMA Earnings Model T-1'!O22/'SQURPHARMA Earnings Model T-1'!O23 -> 0.010025012 | M62: ='SQURPHARMA Earnings Model T-1'!P22/'SQURPHARMA Earnings Model T-1'!P23 -> 0.012249062 | N62: ='SQURPHARMA Earnings Model T-1'!Q22/'SQURPHARMA Earnings Model T-1'!Q23 -> 0.011615995 | P62: =C62+G62+K62 -> 1 | Q62: =D62+H62+L62 -> 1 | R62: =E62+I62+M62 -> 1 | S62: =F62+J62+N62 -> 1
B63: 2023 | C63: ='SQURPHARMA Earnings Model T-1'!S20/'SQURPHARMA Earnings Model T-1'!S23 -> 0.8915582 | D63: ='SQURPHARMA Earnings Model T-1'!T20/'SQURPHARMA Earnings Model T-1'!T23 -> 0.88137188 | E63: ='SQURPHARMA Earnings Model T-1'!U20/'SQURPHARMA Earnings Model T-1'!U23 -> 0.89167262 | F63: ='SQURPHARMA Earnings Model T-1'!V20/'SQURPHARMA Earnings Model T-1'!V23 -> 0.64788888 | G63: ='SQURPHARMA Earnings Model T-1'!S21/'SQURPHARMA Earnings Model T-1'!S23 -> 0.096649085 | H63: ='SQURPHARMA Earnings Model T-1'!T21/'SQURPHARMA Earnings Model T-1'!T23 -> 0.10422841 | I63: ='SQURPHARMA Earnings Model T-1'!U21/'SQURPHARMA Earnings Model T-1'!U23 -> 0.092068253 | J63: ='SQURPHARMA Earnings Model T-1'!V21/'SQURPHARMA Earnings Model T-1'!V23 -> 0.31917545 | K63: ='SQURPHARMA Earnings Model T-1'!S22/'SQURPHARMA Earnings Model T-1'!S23 -> 0.011792718 | L63: ='SQURPHARMA Earnings Model T-1'!T22/'SQURPHARMA Earnings Model T-1'!T23 -> 0.014399705 | M63: ='SQURPHARMA Earnings Model T-1'!U22/'SQURPHARMA Earnings Model T-1'!U23 -> 0.016259125 | N63: ='SQURPHARMA Earnings Model T-1'!V22/'SQURPHARMA Earnings Model T-1'!V23 -> 0.032935672 | P63: =C63+G63+K63 -> 1 | Q63: =D63+H63+L63 -> 1 | R63: =E63+I63+M63 -> 1 | S63: =F63+J63+N63 -> 1
B64: 2024 | C64: ='SQURPHARMA Earnings Model T-1'!X20/'SQURPHARMA Earnings Model T-1'!X23 -> 0.85749092 | D64: ='SQURPHARMA Earnings Model T-1'!Y20/'SQURPHARMA Earnings Model T-1'!Y23 -> 0.855819 | E64: ='SQURPHARMA Earnings Model T-1'!Z20/'SQURPHARMA Earnings Model T-1'!Z23 -> 0.86898556 | G64: ='SQURPHARMA Earnings Model T-1'!X21/'SQURPHARMA Earnings Model T-1'!X23 -> 0.12321528 | H64: ='SQURPHARMA Earnings Model T-1'!Y21/'SQURPHARMA Earnings Model T-1'!Y23 -> 0.12745202 | I64: ='SQURPHARMA Earnings Model T-1'!Z21/'SQURPHARMA Earnings Model T-1'!Z23 -> 0.12004028 | K64: ='SQURPHARMA Earnings Model T-1'!X22/'SQURPHARMA Earnings Model T-1'!X23 -> 0.019293801 | L64: ='SQURPHARMA Earnings Model T-1'!Y22/'SQURPHARMA Earnings Model T-1'!Y23 -> 0.016728978 | M64: ='SQURPHARMA Earnings Model T-1'!Z22/'SQURPHARMA Earnings Model T-1'!Z23 -> 0.010974155 | P64: =C64+G64+K64 -> 1 | Q64: =D64+H64+L64 -> 1 | R64: =E64+I64+M64 -> 1 | S64: =F64+J64+N64 -> 0
B65: Average | C65: =AVERAGE(C60:C64) -> 0.88214606 | D65: =AVERAGE(D60:D64) -> 0.87381677 | E65: =AVERAGE(E60:E64) -> 0.87832819 | F65: =AVERAGE(F60:F63) -> 0.81642452 | G65: =AVERAGE(G60:G64) -> 0.11358053 | H65: =AVERAGE(H60:H64) -> 0.11862181 | I65: =AVERAGE(I60:I64) -> 0.11342854 | J65: =AVERAGE(J60:J63) -> 0.17181811 | K65: =AVERAGE(K60:K64) -> 0.0062195744 | L65: =AVERAGE(L60:L64) -> 0.0082307881 | M65: =AVERAGE(M60:M64) -> 0.0078969624 | N65: =AVERAGE(N60:N63) -> 0.011138599
B67: Interest rate
B68: Long Term Loan - Current Portion | F68: =5%+10.01% -> 0.1501
B69: Long Term Loan | F69: =5.25%+10.48% -> 0.1573
D73: Unclaimed Dividend | J73: Trade Payable
C74: Q1 | D74: Q2 | E74: Q3 | F74: Q4 | K74: Q4, 2023-24 | L74: Q1, 2024 | M74: Q2, 2024 | N74: Q3, 2025
D75: =('SQURPHARMA Earnings Model T-1'!E103-'SQURPHARMA Earnings Model T-1'!D103)/'SQURPHARMA Earnings Model T-1'!D103 -> -0.0042516058 | E75: =('SQURPHARMA Earnings Model T-1'!F103-'SQURPHARMA Earnings Model T-1'!E103)/'SQURPHARMA Earnings Model T-1'!E103 -> -0.00852414 | F75: =('SQURPHARMA Earnings Model T-1'!G103-'SQURPHARMA Earnings Model T-1'!F103)/'SQURPHARMA Earnings Model T-1'!F103 -> 0.13918929 | J75: COGS | K75: ='SQURPHARMA Earnings Model T-1'!V18 -> 10473.874 | L75: ='SQURPHARMA Earnings Model T-1'!X18 -> 8828.4597 | M75: ='SQURPHARMA Earnings Model T-1'!Y18 -> 11064.972 | N75: ='SQURPHARMA Earnings Model T-1'!Z18 -> 10451.314
C76: =('SQURPHARMA Earnings Model T-1'!I103-'SQURPHARMA Earnings Model T-1'!G103)/'SQURPHARMA Earnings Model T-1'!G103 -> -0.72437338 | D76: =('SQURPHARMA Earnings Model T-1'!J103-'SQURPHARMA Earnings Model T-1'!I103)/'SQURPHARMA Earnings Model T-1'!I103 -> -0.03865793 | E76: =('SQURPHARMA Earnings Model T-1'!K103-'SQURPHARMA Earnings Model T-1'!J103)/'SQURPHARMA Earnings Model T-1'!J103 -> -0.25306885 | F76: =('SQURPHARMA Earnings Model T-1'!L103-'SQURPHARMA Earnings Model T-1'!K103)/'SQURPHARMA Earnings Model T-1'!K103 -> 0.74591408 | J76: Payables | K76: 1455.4283 | L76: 1532.3647 | M76: 1325.421 | N76: 1260.5371
C77: =('SQURPHARMA Earnings Model T-1'!N103-'SQURPHARMA Earnings Model T-1'!L103)/'SQURPHARMA Earnings Model T-1'!L103 -> -0.018405161 | D77: =('SQURPHARMA Earnings Model T-1'!O103-'SQURPHARMA Earnings Model T-1'!N103)/'SQURPHARMA Earnings Model T-1'!N103 -> -0.011162117 | E77: =('SQURPHARMA Earnings Model T-1'!P103-'SQURPHARMA Earnings Model T-1'!O103)/'SQURPHARMA Earnings Model T-1'!O103 -> -0.012576946 | F77: =('SQURPHARMA Earnings Model T-1'!Q103-'SQURPHARMA Earnings Model T-1'!P103)/'SQURPHARMA Earnings Model T-1'!P103 -> 0.2796899 | J77: Ratio | K77: =K76/K75 -> 0.13895797 | L77: =L76/L75 -> 0.17357101 | M77: =M76/M75 -> 0.1197853 | N77: =N76/N75 -> 0.12061039
C78: =('SQURPHARMA Earnings Model T-1'!S103-'SQURPHARMA Earnings Model T-1'!Q103)/'SQURPHARMA Earnings Model T-1'!Q103 -> -0.044073021 | D78: =('SQURPHARMA Earnings Model T-1'!T103-'SQURPHARMA Earnings Model T-1'!S103)/'SQURPHARMA Earnings Model T-1'!S103 -> -0.0098731973 | E78: =('SQURPHARMA Earnings Model T-1'!U103-'SQURPHARMA Earnings Model T-1'!T103)/'SQURPHARMA Earnings Model T-1'!T103 -> 0.6047041 | F78: =('SQURPHARMA Earnings Model T-1'!V103-'SQURPHARMA Earnings Model T-1'!U103)/'SQURPHARMA Earnings Model T-1'!U103 -> -0.20500827 | J78: Average | K78: =AVERAGE(K77:N77) -> 0.13823117
B79: Average | C79: =AVERAGE(C76:C78) -> -0.26228385 | D79: =AVERAGE(D75:D78) -> -0.015986213 | E79: =AVERAGE(E75:E78) -> 0.082633542 | F79: =AVERAGE(F75:F78) -> 0.23994625
B82: Current tax liability
C83: Q1 | D83: Q2 | E83: Q3 | F83: Q4
B84: 2020 | D84: =('SQURPHARMA Earnings Model T-1'!E104-'SQURPHARMA Earnings Model T-1'!D104)/'SQURPHARMA Earnings Model T-1'!D104 -> 0.14800432
B85: 2021 | C85: =('SQURPHARMA Earnings Model T-1'!I104-'SQURPHARMA Earnings Model T-1'!G104)/'SQURPHARMA Earnings Model T-1'!G104 -> -1 | D85: =('SQURPHARMA Earnings Model T-1'!J104-'SQURPHARMA Earnings Model T-1'!I104)/'SQURPHARMA Earnings Model T-1'!I104 -> #DIV/0! | E85: =('SQURPHARMA Earnings Model T-1'!K104-'SQURPHARMA Earnings Model T-1'!J104)/'SQURPHARMA Earnings Model T-1'!J104 -> -0.35634449 | F85: =('SQURPHARMA Earnings Model T-1'!L104-'SQURPHARMA Earnings Model T-1'!K104)/'SQURPHARMA Earnings Model T-1'!K104 -> 0.30487796
B86: 2022 | C86: =('SQURPHARMA Earnings Model T-1'!N104-'SQURPHARMA Earnings Model T-1'!L104)/'SQURPHARMA Earnings Model T-1'!L104 -> 0.59400379 | D86: =('SQURPHARMA Earnings Model T-1'!O104-'SQURPHARMA Earnings Model T-1'!N104)/'SQURPHARMA Earnings Model T-1'!N104 -> 0.21322548 | E86: =('SQURPHARMA Earnings Model T-1'!P104-'SQURPHARMA Earnings Model T-1'!O104)/'SQURPHARMA Earnings Model T-1'!O104 -> -0.22736137 | F86: =('SQURPHARMA Earnings Model T-1'!Q104-'SQURPHARMA Earnings Model T-1'!P104)/'SQURPHARMA Earnings Model T-1'!P104 -> -0.73854301
B87: 2023 | C87: =('SQURPHARMA Earnings Model T-1'!S104-'SQURPHARMA Earnings Model T-1'!Q104)/'SQURPHARMA Earnings Model T-1'!Q104 -> 1.6101521 | D87: =('SQURPHARMA Earnings Model T-1'!T104-'SQURPHARMA Earnings Model T-1'!S104)/'SQURPHARMA Earnings Model T-1'!S104 -> 0.12480562 | E87: =('SQURPHARMA Earnings Model T-1'!U104-'SQURPHARMA Earnings Model T-1'!T104)/'SQURPHARMA Earnings Model T-1'!T104 -> 0.17575826 | F87: =('SQURPHARMA Earnings Model T-1'!V104-'SQURPHARMA Earnings Model T-1'!U104)/'SQURPHARMA Earnings Model T-1'!U104 -> -0.25784681
B88: 2024 | C88: =('SQURPHARMA Earnings Model T-1'!X104-'SQURPHARMA Earnings Model T-1'!V104)/'SQURPHARMA Earnings Model T-1'!V104 -> 0.18380876 | D88: =('SQURPHARMA Earnings Model T-1'!Y104-'SQURPHARMA Earnings Model T-1'!X104)/'SQURPHARMA Earnings Model T-1'!X104 -> 0.18056977 | E88: =('SQURPHARMA Earnings Model T-1'!Z104-'SQURPHARMA Earnings Model T-1'!Y104)/'SQURPHARMA Earnings Model T-1'!Y104 -> 0.28405278
B89: Average | C89: =AVERAGE(C84:C88) -> 0.34699117 | D89: =AVERAGE(D86:D88,D84) -> 0.1666513 | E89: =AVERAGE(E84:E88) -> -0.030973705 | F89: =AVERAGE(F84:F88) -> -0.23050395
